[{"version_id":"822398002","version_name":"0.80","version_date":"2017-06-23 05:58:20.000 +0800","version_description":""},{"version_id":"822765779","version_name":"0.81","version_date":"2017-07-03 21:41:12.000 +0800","version_description":"* 新收藏品！<br>* 比賽規則調整，減少輸家付出金額<br>* 修正技能書籍數量顯示錯誤<br>* 修正道具分數加成計算錯誤"},{"version_id":"823234395","version_name":"0.82","version_date":"2017-08-09 23:38:26.000 +0800","version_description":"* 關主難度下降。玩家們的心聲我們聽到了！<br>* 修正收集品、護照章文字與圖案錯誤<br>* 修正低機率過關後卡住的問題<br>* 效能調整與小錯誤修正<br>* 題庫更新與勘誤"},{"version_id":"823344593","version_name":"0.851","version_date":"2017-08-19 23:57:52.000 +0800","version_description":"* 新增連續開啟福袋功能<br>* 顯示收集品系列完成數<br>* 再次修正過關後卡住的問題<br>* 穩定度與畫面調整<br>* 題庫更新與勘誤"},{"version_id":"823528565","version_name":"0.861","version_date":"2017-09-05 21:42:05.000 +0800","version_description":"* 新關卡！挑戰北歐眾神！<br>* 新的商店設計與商品<br>* 新增連續兌換黃金與珍珠功能<br>* 修正大量已知錯誤<br>* 題庫更新與勘誤<br>* 預告：收集品獎勵兌換功能開發中"},{"version_id":"823659298","version_name":"0.871","version_date":"2017-09-15 03:32:35.000 +0800","version_description":"* 完成一組收集品系列，可免費兌換珍珠x10。之前已完成的將自動轉換<br>* 高級保險箱容量大幅增加，之前已購買的將自動升級<br>* 提示功能改良，閱讀列表後小紅點就會消失<br>* 金幣不足時，視窗會出現保險箱快捷按鈕<br>* 預告：自訂題庫功能開發中"},{"version_id":"823791169","version_name":"0.880","version_date":"2017-09-27 09:05:44.000 +0800","version_description":"* 中秋節限定，好友對戰開放專屬佈景以及題庫<br>* 開放玩家自訂暱稱功能 (履歷點擊頭像)<br>* 降低知識升級價格，之前調整不合理之處和玩家們說聲抱歉<br>* 好友對戰會自動儲存設定<br>* 更新至 iOS 11.0<br>* 預告：自訂題庫功能仍在開發中"},{"version_id":"823834765","version_name":"0.882","version_date":"2017-09-29 00:14:02.000 +0800","version_description":"* 緊急修正閃退問題<br>* 中秋節限定，好友對戰專屬佈景以及題庫<br>* 開放玩家自訂暱稱功能 (履歷點擊頭像)<br>* 降低知識升級價格，之前調整不合理之處和玩家們說聲抱歉<br>* 好友對戰會自動儲存設定<br>* iOS SDK 11.0 相容性更新<br>* 預告：自訂題庫功能開發中"},{"version_id":"824042514","version_name":"0.891","version_date":"2017-10-19 00:29:37.000 +0800","version_description":"* 新增自訂題庫功能 (履歷&gt;設定&gt;自訂題庫)<br>* 新增挑戰獎勵：高級福袋<br>* 平衡度調整<br>* 修正檢視好友資料時，網路速度太慢造成閃退的錯誤<br>* 修正連續答對 10 題以上沒有顯示英文標題<br>* 使用介面流暢度調整<br>* 調整網路參數，降低連線失敗機率"},{"version_id":"824169633","version_name":"0.900","version_date":"2017-10-27 15:13:16.000 +0800","version_description":"* 萬聖節限定，好友對戰佈景以及題庫<br>* 全新的 7 首對戰背景音樂<br>* 新收集品上架<br>* 修正執法者造型未解鎖錯誤<br>* 修正關閉對話功能在結算畫面無效問題<br>* 預告：新關卡以及功能道具開發中"},{"version_id":"824290031","version_name":"0.910","version_date":"2017-11-08 18:28:35.000 +0800","version_description":"* 針對 iPhone X 畫面調整與優化<br>* 購買造型後就會自動啟用，不用多點一次<br>* 小錯誤修正"},{"version_id":"825578931","version_name":"0.924","version_date":"2018-01-10 19:09:40.000 +0800","version_description":"* 介面流暢度提升30%<br>* 修正網路不穩定時對戰，偶發性的程式錯誤<br>* 修正某些情況上方狀態列沒有同步更新問題<br>* 修正最後一關解鎖判斷錯誤<br>* 採納玩家建議，新增金幣獎勵。但我們發現金幣獎勵在初期是續玩的重要資源，在後期可能就只是安慰獎了。未來會再視情況調整平衡"},{"version_id":"825717651","version_name":"0.936","version_date":"2018-02-14 19:09:22.000 +0800","version_description":"* 慶祝農曆新年，專屬主題以及多種優惠商品歡迎選購！<br>* 首頁大改版！更簡潔直覺。不習慣的人可至系統功能切換成舊版本<br>* 全新的『能力增幅道具』可有效協助戰勝關主<br>* 現在開始每次升級會隨機獲得獎勵。舊玩家將依照等級換算一次領取！<br>* 水晶、羅盤等舊道具即將廢除。用完後不再顯示於列表中<br>* 開放自訂題庫數量至3個，並可以設定是否顯示於遊戲列表中<br>* 知識圖示大改版！更容易辨識<br>* 視窗大改版！快速切換不同功能<br>* 題庫更新與勘誤<br>* 多項小錯誤修正"},{"version_id":"826503017","version_name":"0.938","version_date":"2018-03-30 18:52:21.000 +0800","version_description":"* 強化『知識寶典』分數加成上調為 30%<br>* 修正新年商品下架時間設定錯誤<br>* 修正免費對戰福袋倒數計時錯誤<br>* 小型錯誤修正"},{"version_id":"827852145","version_name":"0.983","version_date":"2019-09-17 05:00:44.000 +0800","version_description":"* 小幅優化"},{"version_id":"827852145","version_name":"0.950","version_date":"2019-05-28 17:12:42.000 +0800","version_description":"* 題庫更新與勘誤<br>* 效能調整以及錯誤修正"},{"version_id":"827852145","version_name":"0.943","version_date":"2018-12-09 22:29:24.000 +0800","version_description":"*《爐石戰記》題庫全新上線，好友對戰連線功能中隨時隨地、全方位挑戰和鍛鍊爐石知識，也許你就是下一位電競世界冠軍！(本活動由暴雪社群贊助)<br>* 修正無法取得 FACEBOOK 好友列表問題<br>* 作業系統函式庫更新<br>* 效能調整以及錯誤修正"},{"version_id":"827852145","version_name":"0.939","version_date":"2018-07-12 19:45:01.000 +0800","version_description":"* 效能調整以及錯誤修正<br>* 更新第三方功能套件以符合最新的 GDPR 隱私權保護規範"},{"version_id":"829490771","version_name":"0.943","version_date":"2018-12-09 22:29:24.000 +0800","version_description":"*《爐石戰記》題庫全新上線，好友對戰連線功能中隨時隨地、全方位挑戰和鍛鍊爐石知識，也許你就是下一位電競世界冠軍！(本活動由暴雪社群贊助)<br>* 修正無法取得 FACEBOOK 好友列表問題<br>* 作業系統函式庫更新<br>* 效能調整以及錯誤修正"},{"version_id":"831456880","version_name":"0.950","version_date":"2019-05-28 17:12:42.000 +0800","version_description":"* 題庫更新與勘誤<br>* 效能調整以及錯誤修正"},{"version_id":"832777321","version_name":"0.983","version_date":"2019-09-17 05:00:44.000 +0800","version_description":"* 小幅優化"},{"version_id":"833977199","version_name":"0.990","version_date":"2019-12-13 06:17:55.000 +0800","version_description":"* 新關卡！印度神話篇<br>* 大量新收集品<br>* 題庫更新與勘誤"},{"version_id":"834012378","version_name":"0.991","version_date":"2019-12-15 22:30:28.000 +0800","version_description":"* 新關卡！印度神話篇<br>* 大量新收集品<br>* 題庫更新與勘誤<br>* 修正新關卡無法解鎖的問題"},{"version_id":"834286873","version_name":"0.992","version_date":"2020-01-23 04:08:26.000 +0800","version_description":"* 慶祝春節，實驗性功能大方送<br>* 每日限定三次能力增幅道具試用，打敗關主更容易<br>* 好友對戰人名可顯示玩家自訂暱稱<br>* 看廣告即可獲得免費福袋，大幅增加每日好友對戰次數<br>* 備註：春節假期過後，新系統會視情況決定保留或還原"},{"version_id":"834563125","version_name":"0.993","version_date":"2020-02-03 01:24:56.000 +0800","version_description":"* 修正某些情況下無法取得獎品福袋以及試用道具的錯誤"},{"version_id":"835412111","version_name":"0.996","version_date":"2020-04-06 01:33:53.000 +0800","version_description":"* 穩定度調整"},{"version_id":"836009419","version_name":"0.997","version_date":"2020-05-20 07:39:03.000 +0800","version_description":"* 依照Facebook平台政策調整帳號綁定流程。可能還需要幾天才會恢復正常。"},{"version_id":"837255051","version_name":"0.998","version_date":"2020-08-09 17:55:08.000 +0800","version_description":"- 新增「使用Apple登入」帳號功能<br>- 穩定度調整<br>- 題庫更新與勘誤"},{"version_id":"838243442","version_name":"0.999","version_date":"2020-10-17 01:10:14.000 +0800","version_description":"- 穩定度調整<br>- 程式函式庫更新"},{"version_id":"840819481","version_name":"1.000","version_date":"2021-03-10 12:29:07.000 +0800","version_description":"* 穩定度調整<br>* 程式函式庫更新"},{"version_id":"841274665","version_name":"1.001","version_date":"2021-04-12 14:20:39.000 +0800","version_description":"* 穩定度調整<br>* 更新程式函式庫"}]