[{"version_id":"16420300","version_name":"6.90","version_date":"","version_description":""},{"version_id":"16420300","version_name":"6.90","version_date":"","version_description":""},{"version_id":"16420300","version_name":"6.90","version_date":"","version_description":""},{"version_id":"16420300","version_name":"6.90","version_date":"","version_description":""},{"version_id":"16420300","version_name":"6.90","version_date":"","version_description":""},{"version_id":"165712644","version_name":"7.01","version_date":"","version_description":""},{"version_id":"165712644","version_name":"7.01","version_date":"","version_description":""},{"version_id":"165712644","version_name":"7.01","version_date":"","version_description":""},{"version_id":"165712644","version_name":"7.01","version_date":"","version_description":""},{"version_id":"165712644","version_name":"7.01","version_date":"","version_description":""},{"version_id":"630602680","version_name":"7.02","version_date":"","version_description":""},{"version_id":"630602680","version_name":"7.02","version_date":"","version_description":""},{"version_id":"630602680","version_name":"7.02","version_date":"","version_description":""},{"version_id":"630602680","version_name":"7.02","version_date":"","version_description":""},{"version_id":"630602680","version_name":"7.02","version_date":"","version_description":""},{"version_id":"811544338","version_name":"7.21","version_date":"","version_description":""},{"version_id":"811544338","version_name":"7.21","version_date":"","version_description":""},{"version_id":"811544338","version_name":"7.21","version_date":"","version_description":""},{"version_id":"811544338","version_name":"7.21","version_date":"","version_description":""},{"version_id":"811544338","version_name":"7.21","version_date":"","version_description":""},{"version_id":"813002602","version_name":"8.32","version_date":"","version_description":""},{"version_id":"813002602","version_name":"8.32","version_date":"","version_description":""},{"version_id":"813002602","version_name":"8.32","version_date":"","version_description":""},{"version_id":"813002602","version_name":"8.32","version_date":"","version_description":""},{"version_id":"813002602","version_name":"8.32","version_date":"","version_description":""},{"version_id":"815225272","version_name":"8.53","version_date":"","version_description":""},{"version_id":"815225272","version_name":"8.53","version_date":"","version_description":""},{"version_id":"815225272","version_name":"8.53","version_date":"","version_description":""},{"version_id":"815225272","version_name":"8.53","version_date":"","version_description":""},{"version_id":"815225272","version_name":"8.53","version_date":"","version_description":""},{"version_id":"815820988","version_name":"9.0","version_date":"","version_description":""},{"version_id":"815820988","version_name":"9.0","version_date":"","version_description":""},{"version_id":"815820988","version_name":"9.0","version_date":"","version_description":""},{"version_id":"815820988","version_name":"9.0","version_date":"","version_description":""},{"version_id":"815820988","version_name":"9.0","version_date":"","version_description":""},{"version_id":"816789424","version_name":"10.0","version_date":"","version_description":""},{"version_id":"816789424","version_name":"10.0","version_date":"","version_description":""},{"version_id":"816789424","version_name":"10.0","version_date":"","version_description":""},{"version_id":"816789424","version_name":"10.0","version_date":"","version_description":""},{"version_id":"816789424","version_name":"10.0","version_date":"","version_description":""},{"version_id":"816904677","version_name":"10.02","version_date":"2016-04-06 02:26:56.000 +0800","version_description":"Added \"Open in\" button back in Files."},{"version_id":"816904677","version_name":"10.02","version_date":"2016-04-06 02:26:56.000 +0800","version_description":"Added \"Open in\" button back in Files."},{"version_id":"816904677","version_name":"10.02","version_date":"2016-04-06 02:26:56.000 +0800","version_description":"Added \"Open in\" button back in Files."},{"version_id":"816904677","version_name":"10.02","version_date":"2016-04-06 02:26:56.000 +0800","version_description":"Added \"Open in\" button back in Files."},{"version_id":"816904677","version_name":"10.02","version_date":"2016-04-06 02:26:56.000 +0800","version_description":"Added \"Open in\" button back in Files."},{"version_id":"817420682","version_name":"11.0","version_date":"2016-05-17 21:48:33.000 +0800","version_description":"1. Added a better Audio Player. Now supports pause/forward/backward from Control Center and Lock Screen.<br>2. Now supports email multiple files without compression.<br>3. Fixed UI defects."},{"version_id":"817420682","version_name":"11.0","version_date":"2016-05-17 21:48:33.000 +0800","version_description":"1. Added a better Audio Player. Now supports pause/forward/backward from Control Center and Lock Screen.<br>2. Now supports email multiple files without compression.<br>3. Fixed UI defects."},{"version_id":"817420682","version_name":"11.0","version_date":"2016-05-17 21:48:33.000 +0800","version_description":"1. Added a better Audio Player. Now supports pause/forward/backward from Control Center and Lock Screen.<br>2. Now supports email multiple files without compression.<br>3. Fixed UI defects."},{"version_id":"817420682","version_name":"11.0","version_date":"2016-05-17 21:48:33.000 +0800","version_description":"1. Added a better Audio Player. Now supports pause/forward/backward from Control Center and Lock Screen.<br>2. Now supports email multiple files without compression.<br>3. Fixed UI defects."},{"version_id":"817420682","version_name":"11.0","version_date":"2016-05-17 21:48:33.000 +0800","version_description":"1. Added a better Audio Player. Now supports pause/forward/backward from Control Center and Lock Screen.<br>2. Now supports email multiple files without compression.<br>3. Fixed UI defects."},{"version_id":"817440731","version_name":"11.01","version_date":"2016-05-18 14:46:29.000 +0800","version_description":"1. Added a better Audio Player. Now supports pause/forward/backward from Control Center and Lock Screen.<br>2. Now supports email multiple files without compression.<br>3. Fixed UI defects."},{"version_id":"817440731","version_name":"11.01","version_date":"2016-05-18 14:46:29.000 +0800","version_description":"1. Added a better Audio Player. Now supports pause/forward/backward from Control Center and Lock Screen.<br>2. Now supports email multiple files without compression.<br>3. Fixed UI defects."},{"version_id":"817440731","version_name":"11.01","version_date":"2016-05-18 14:46:29.000 +0800","version_description":"1. Added a better Audio Player. Now supports pause/forward/backward from Control Center and Lock Screen.<br>2. Now supports email multiple files without compression.<br>3. Fixed UI defects."},{"version_id":"817440731","version_name":"11.01","version_date":"2016-05-18 14:46:29.000 +0800","version_description":"1. Added a better Audio Player. Now supports pause/forward/backward from Control Center and Lock Screen.<br>2. Now supports email multiple files without compression.<br>3. Fixed UI defects."},{"version_id":"817440731","version_name":"11.01","version_date":"2016-05-18 14:46:29.000 +0800","version_description":"1. Added a better Audio Player. Now supports pause/forward/backward from Control Center and Lock Screen.<br>2. Now supports email multiple files without compression.<br>3. Fixed UI defects."},{"version_id":"817540944","version_name":"11.02","version_date":"2016-05-27 11:52:21.000 +0800","version_description":"1.Fixed the issue that the App keeps asking for user’s review when No is selected."},{"version_id":"817540944","version_name":"11.02","version_date":"2016-05-27 11:52:21.000 +0800","version_description":"1.Fixed the issue that the App keeps asking for user’s review when No is selected."},{"version_id":"817540944","version_name":"11.02","version_date":"2016-05-27 11:52:21.000 +0800","version_description":"1.Fixed the issue that the App keeps asking for user’s review when No is selected."},{"version_id":"817540944","version_name":"11.02","version_date":"2016-05-27 11:52:21.000 +0800","version_description":"1.Fixed the issue that the App keeps asking for user’s review when No is selected."},{"version_id":"817540944","version_name":"11.02","version_date":"2016-05-27 11:52:21.000 +0800","version_description":"1.Fixed the issue that the App keeps asking for user’s review when No is selected."},{"version_id":"817619517","version_name":"11.03","version_date":"2016-06-04 02:49:03.000 +0800","version_description":"修复寻求用户评价的一个问题。"},{"version_id":"817619517","version_name":"11.03","version_date":"2016-06-04 02:49:03.000 +0800","version_description":"修复寻求用户评价的一个问题。"},{"version_id":"817619517","version_name":"11.03","version_date":"2016-06-04 02:49:03.000 +0800","version_description":"修复寻求用户评价的一个问题。"},{"version_id":"817619517","version_name":"11.03","version_date":"2016-06-04 02:49:03.000 +0800","version_description":"修复寻求用户评价的一个问题。"},{"version_id":"817619517","version_name":"11.03","version_date":"2016-06-04 02:49:03.000 +0800","version_description":"修复寻求用户评价的一个问题。"},{"version_id":"817765797","version_name":"11.04","version_date":"2016-06-15 00:01:32.000 +0800","version_description":"Bug fixes."},{"version_id":"817765797","version_name":"11.04","version_date":"2016-06-15 00:01:32.000 +0800","version_description":"Bug fixes."},{"version_id":"817765797","version_name":"11.04","version_date":"2016-06-15 00:01:32.000 +0800","version_description":"Bug fixes."},{"version_id":"817765797","version_name":"11.04","version_date":"2016-06-15 00:01:32.000 +0800","version_description":"Bug fixes."},{"version_id":"817765797","version_name":"11.04","version_date":"2016-06-15 00:01:32.000 +0800","version_description":"Bug fixes."},{"version_id":"819744196","version_name":"12.0","version_date":"2016-11-17 16:34:37.000 +0800","version_description":"1. Build for iOS 10.<br>2. Added Transfer File to iZip Pro in Settings.<br>3. Added Swipe Gesture support.<br>4. Fixed various defects."},{"version_id":"819744196","version_name":"12.0","version_date":"2016-11-17 16:34:37.000 +0800","version_description":"1. Build for iOS 10.<br>2. Added Transfer File to iZip Pro in Settings.<br>3. Added Swipe Gesture support.<br>4. Fixed various defects."},{"version_id":"819744196","version_name":"12.0","version_date":"2016-11-17 16:34:37.000 +0800","version_description":"1. Build for iOS 10.<br>2. Added Transfer File to iZip Pro in Settings.<br>3. Added Swipe Gesture support.<br>4. Fixed various defects."},{"version_id":"819744196","version_name":"12.0","version_date":"2016-11-17 16:34:37.000 +0800","version_description":"1. Build for iOS 10.<br>2. Added Transfer File to iZip Pro in Settings.<br>3. Added Swipe Gesture support.<br>4. Fixed various defects."},{"version_id":"819744196","version_name":"12.0","version_date":"2016-11-17 16:34:37.000 +0800","version_description":"1. Build for iOS 10.<br>2. Added Transfer File to iZip Pro in Settings.<br>3. Added Swipe Gesture support.<br>4. Fixed various defects."},{"version_id":"821275370","version_name":"13.0","version_date":"2017-03-12 14:13:57.000 +0800","version_description":"Updated Dropbox SDK."},{"version_id":"821275370","version_name":"13.0","version_date":"2017-03-12 14:13:57.000 +0800","version_description":"Updated Dropbox SDK."},{"version_id":"821275370","version_name":"13.0","version_date":"2017-03-12 14:13:57.000 +0800","version_description":"Updated Dropbox SDK."},{"version_id":"821275370","version_name":"13.0","version_date":"2017-03-12 14:13:57.000 +0800","version_description":"Updated Dropbox SDK."},{"version_id":"821275370","version_name":"13.0","version_date":"2017-03-12 14:13:57.000 +0800","version_description":"Updated Dropbox SDK."},{"version_id":"821341182","version_name":"13.01","version_date":"2017-03-16 23:54:13.000 +0800","version_description":"修复登陆Dropbox的问题。"},{"version_id":"821341182","version_name":"13.01","version_date":"2017-03-16 23:54:13.000 +0800","version_description":"修复登陆Dropbox的问题。"},{"version_id":"821341182","version_name":"13.01","version_date":"2017-03-16 23:54:13.000 +0800","version_description":"修复登陆Dropbox的问题。"},{"version_id":"821341182","version_name":"13.01","version_date":"2017-03-16 23:54:13.000 +0800","version_description":"修复登陆Dropbox的问题。"},{"version_id":"821341182","version_name":"13.01","version_date":"2017-03-16 23:54:13.000 +0800","version_description":"修复登陆Dropbox的问题。"},{"version_id":"821415094","version_name":"13.50","version_date":"2017-08-23 02:19:56.000 +0800","version_description":"Added fast forward and backward support for music playback."},{"version_id":"821415094","version_name":"13.50","version_date":"2017-08-23 02:19:56.000 +0800","version_description":"Added fast forward and backward support for music playback."},{"version_id":"821415094","version_name":"13.50","version_date":"2017-08-23 02:19:56.000 +0800","version_description":"Added fast forward and backward support for music playback."},{"version_id":"821415094","version_name":"13.50","version_date":"2017-08-23 02:19:56.000 +0800","version_description":"Added fast forward and backward support for music playback."},{"version_id":"821415094","version_name":"13.50","version_date":"2017-08-23 02:19:56.000 +0800","version_description":"Added fast forward and backward support for music playback."},{"version_id":"823632436","version_name":"14.0","version_date":"2017-09-15 13:38:44.000 +0800","version_description":"Build for iOS 11. Now supports Document Browser."},{"version_id":"823632436","version_name":"14.0","version_date":"2017-09-15 13:38:44.000 +0800","version_description":"Build for iOS 11. Now supports Document Browser."},{"version_id":"823632436","version_name":"14.0","version_date":"2017-09-15 13:38:44.000 +0800","version_description":"Build for iOS 11. Now supports Document Browser."},{"version_id":"823632436","version_name":"14.0","version_date":"2017-09-15 13:38:44.000 +0800","version_description":"Build for iOS 11. Now supports Document Browser."},{"version_id":"823632436","version_name":"14.0","version_date":"2017-09-15 13:38:44.000 +0800","version_description":"Build for iOS 11. Now supports Document Browser."},{"version_id":"823720346","version_name":"14.01","version_date":"2017-09-26 22:35:05.000 +0800","version_description":"Added Preview Video and updated Screenshots."},{"version_id":"823720346","version_name":"14.01","version_date":"2017-09-26 22:35:05.000 +0800","version_description":"Added Preview Video and updated Screenshots."},{"version_id":"823720346","version_name":"14.01","version_date":"2017-09-26 22:35:05.000 +0800","version_description":"Added Preview Video and updated Screenshots."},{"version_id":"823720346","version_name":"14.01","version_date":"2017-09-26 22:35:05.000 +0800","version_description":"Added Preview Video and updated Screenshots."},{"version_id":"823720346","version_name":"14.01","version_date":"2017-09-26 22:35:05.000 +0800","version_description":"Added Preview Video and updated Screenshots."},{"version_id":"823973045","version_name":"15.01","version_date":"2017-10-11 18:28:20.000 +0800","version_description":"1. Updated Photo Framework and added support for HEIC image format introduced in iOS 11.<br>2. Fixed App crashing in iOS 11 when saving images to Camera Roll.<br>3. Fixed the issue of opening a document in another App in iOS 11."},{"version_id":"823973045","version_name":"15.01","version_date":"2017-10-11 18:28:20.000 +0800","version_description":"1. Updated Photo Framework and added support for HEIC image format introduced in iOS 11.<br>2. Fixed App crashing in iOS 11 when saving images to Camera Roll.<br>3. Fixed the issue of opening a document in another App in iOS 11."},{"version_id":"823973045","version_name":"15.01","version_date":"2017-10-11 18:28:20.000 +0800","version_description":"1. Updated Photo Framework and added support for HEIC image format introduced in iOS 11.<br>2. Fixed App crashing in iOS 11 when saving images to Camera Roll.<br>3. Fixed the issue of opening a document in another App in iOS 11."},{"version_id":"823973045","version_name":"15.01","version_date":"2017-10-11 18:28:20.000 +0800","version_description":"1. Updated Photo Framework and added support for HEIC image format introduced in iOS 11.<br>2. Fixed App crashing in iOS 11 when saving images to Camera Roll.<br>3. Fixed the issue of opening a document in another App in iOS 11."},{"version_id":"823973045","version_name":"15.01","version_date":"2017-10-11 18:28:20.000 +0800","version_description":"1. Updated Photo Framework and added support for HEIC image format introduced in iOS 11.<br>2. Fixed App crashing in iOS 11 when saving images to Camera Roll.<br>3. Fixed the issue of opening a document in another App in iOS 11."},{"version_id":"824001086","version_name":"15.02","version_date":"2017-10-13 01:33:16.000 +0800","version_description":"Optimized photo compression."},{"version_id":"824001086","version_name":"15.02","version_date":"2017-10-13 01:33:16.000 +0800","version_description":"Optimized photo compression."},{"version_id":"824001086","version_name":"15.02","version_date":"2017-10-13 01:33:16.000 +0800","version_description":"Optimized photo compression."},{"version_id":"824001086","version_name":"15.02","version_date":"2017-10-13 01:33:16.000 +0800","version_description":"Optimized photo compression."},{"version_id":"824001086","version_name":"15.02","version_date":"2017-10-13 01:33:16.000 +0800","version_description":"Optimized photo compression."},{"version_id":"824085235","version_name":"15.03","version_date":"2017-10-20 13:29:58.000 +0800","version_description":"Added support of User Albums in Photos."},{"version_id":"824085235","version_name":"15.03","version_date":"2017-10-20 13:29:58.000 +0800","version_description":"Added support of User Albums in Photos."},{"version_id":"824085235","version_name":"15.03","version_date":"2017-10-20 13:29:58.000 +0800","version_description":"Added support of User Albums in Photos."},{"version_id":"824085235","version_name":"15.03","version_date":"2017-10-20 13:29:58.000 +0800","version_description":"Added support of User Albums in Photos."},{"version_id":"824085235","version_name":"15.03","version_date":"2017-10-20 13:29:58.000 +0800","version_description":"Added support of User Albums in Photos."},{"version_id":"824160958","version_name":"15.05","version_date":"2017-10-27 20:49:26.000 +0800","version_description":"修复无法压缩视频问题。"},{"version_id":"824160958","version_name":"15.05","version_date":"2017-10-27 20:49:26.000 +0800","version_description":"修复无法压缩视频问题。"},{"version_id":"824160958","version_name":"15.05","version_date":"2017-10-27 20:49:26.000 +0800","version_description":"修复无法压缩视频问题。"},{"version_id":"824160958","version_name":"15.05","version_date":"2017-10-27 20:49:26.000 +0800","version_description":"修复无法压缩视频问题。"},{"version_id":"824160958","version_name":"15.05","version_date":"2017-10-27 20:49:26.000 +0800","version_description":"修复无法压缩视频问题。"},{"version_id":"824288551","version_name":"15.06","version_date":"2017-11-06 17:31:03.000 +0800","version_description":"Improved photo quality. Now photos are loaded in original sizes before compression."},{"version_id":"824288551","version_name":"15.06","version_date":"2017-11-06 17:31:03.000 +0800","version_description":"Improved photo quality. Now photos are loaded in original sizes before compression."},{"version_id":"824288551","version_name":"15.06","version_date":"2017-11-06 17:31:03.000 +0800","version_description":"Improved photo quality. Now photos are loaded in original sizes before compression."},{"version_id":"824288551","version_name":"15.06","version_date":"2017-11-06 17:31:03.000 +0800","version_description":"Improved photo quality. Now photos are loaded in original sizes before compression."},{"version_id":"824288551","version_name":"15.06","version_date":"2017-11-06 17:31:03.000 +0800","version_description":"Improved photo quality. Now photos are loaded in original sizes before compression."},{"version_id":"824337227","version_name":"15.07","version_date":"2017-11-09 16:25:02.000 +0800","version_description":"Adjusted display to better support iPhone X and iPad Pro screens."},{"version_id":"824337227","version_name":"15.07","version_date":"2017-11-09 16:25:02.000 +0800","version_description":"Adjusted display to better support iPhone X and iPad Pro screens."},{"version_id":"824337227","version_name":"15.07","version_date":"2017-11-09 16:25:02.000 +0800","version_description":"Adjusted display to better support iPhone X and iPad Pro screens."},{"version_id":"824337227","version_name":"15.07","version_date":"2017-11-09 16:25:02.000 +0800","version_description":"Adjusted display to better support iPhone X and iPad Pro screens."},{"version_id":"824337227","version_name":"15.07","version_date":"2017-11-09 16:25:02.000 +0800","version_description":"Adjusted display to better support iPhone X and iPad Pro screens."},{"version_id":"825224345","version_name":"15.08","version_date":"2017-12-07 00:52:44.000 +0800","version_description":"1. Fixed displaying issues on iPhone X.<br>2. Added support for Face ID.<br>3. Added Default Photo Size in Zip Settings."},{"version_id":"825224345","version_name":"15.08","version_date":"2017-12-07 00:52:44.000 +0800","version_description":"1. Fixed displaying issues on iPhone X.<br>2. Added support for Face ID.<br>3. Added Default Photo Size in Zip Settings."},{"version_id":"825224345","version_name":"15.08","version_date":"2017-12-07 00:52:44.000 +0800","version_description":"1. Fixed displaying issues on iPhone X.<br>2. Added support for Face ID.<br>3. Added Default Photo Size in Zip Settings."},{"version_id":"825224345","version_name":"15.08","version_date":"2017-12-07 00:52:44.000 +0800","version_description":"1. Fixed displaying issues on iPhone X.<br>2. Added support for Face ID.<br>3. Added Default Photo Size in Zip Settings."},{"version_id":"825224345","version_name":"15.08","version_date":"2017-12-07 00:52:44.000 +0800","version_description":"1. Fixed displaying issues on iPhone X.<br>2. Added support for Face ID.<br>3. Added Default Photo Size in Zip Settings."},{"version_id":"826805515","version_name":"15.09","version_date":"2018-04-26 00:08:32.000 +0800","version_description":"Fixed App crashing on iPhone X with iOS 11.3 when FaceID is used."},{"version_id":"826805515","version_name":"15.09","version_date":"2018-04-26 00:08:32.000 +0800","version_description":"Fixed App crashing on iPhone X with iOS 11.3 when FaceID is used."},{"version_id":"826805515","version_name":"15.09","version_date":"2018-04-26 00:08:32.000 +0800","version_description":"Fixed App crashing on iPhone X with iOS 11.3 when FaceID is used."},{"version_id":"826805515","version_name":"15.09","version_date":"2018-04-26 00:08:32.000 +0800","version_description":"Fixed App crashing on iPhone X with iOS 11.3 when FaceID is used."},{"version_id":"826805515","version_name":"15.09","version_date":"2018-04-26 00:08:32.000 +0800","version_description":"Fixed App crashing on iPhone X with iOS 11.3 when FaceID is used."},{"version_id":"826885942","version_name":"15.10","version_date":"2018-05-01 21:14:37.000 +0800","version_description":"Various bug fixes."},{"version_id":"826885942","version_name":"15.10","version_date":"2018-05-01 21:14:37.000 +0800","version_description":"Various bug fixes."},{"version_id":"826885942","version_name":"15.10","version_date":"2018-05-01 21:14:37.000 +0800","version_description":"Various bug fixes."},{"version_id":"826885942","version_name":"15.10","version_date":"2018-05-01 21:14:37.000 +0800","version_description":"Various bug fixes."},{"version_id":"826885942","version_name":"15.10","version_date":"2018-05-01 21:14:37.000 +0800","version_description":"Various bug fixes."},{"version_id":"826898517","version_name":"15.11","version_date":"2018-05-02 20:25:23.000 +0800","version_description":"Fixed the \"Operation Failed\" issue when extracting certain Zip files."},{"version_id":"826898517","version_name":"15.11","version_date":"2018-05-02 20:25:23.000 +0800","version_description":"Fixed the \"Operation Failed\" issue when extracting certain Zip files."},{"version_id":"826898517","version_name":"15.11","version_date":"2018-05-02 20:25:23.000 +0800","version_description":"Fixed the \"Operation Failed\" issue when extracting certain Zip files."},{"version_id":"826898517","version_name":"15.11","version_date":"2018-05-02 20:25:23.000 +0800","version_description":"Fixed the \"Operation Failed\" issue when extracting certain Zip files."},{"version_id":"826898517","version_name":"15.11","version_date":"2018-05-02 20:25:23.000 +0800","version_description":"Fixed the \"Operation Failed\" issue when extracting certain Zip files."},{"version_id":"826957431","version_name":"15.50","version_date":"2018-05-08 18:25:47.000 +0800","version_description":"1. Added support for more compressed file types. Now iZip extracts:<br>  - Encrypted RAR files.<br>  - Encrypted 7Z files.<br>  - TGZ files. <br>  - BZip and TBZ files. <br>2. Fixed the encoding issue when showing text files in foreign languages.<br>3. Fixed app crashing when opening certain documents.<br>4. Better handling of FaceID/TouchID to unlock screen."},{"version_id":"826957431","version_name":"15.50","version_date":"2018-05-08 18:25:47.000 +0800","version_description":"1. Added support for more compressed file types. Now iZip extracts:<br>  - Encrypted RAR files.<br>  - Encrypted 7Z files.<br>  - TGZ files. <br>  - BZip and TBZ files. <br>2. Fixed the encoding issue when showing text files in foreign languages.<br>3. Fixed app crashing when opening certain documents.<br>4. Better handling of FaceID/TouchID to unlock screen."},{"version_id":"826957431","version_name":"15.50","version_date":"2018-05-08 18:25:47.000 +0800","version_description":"1. Added support for more compressed file types. Now iZip extracts:<br>  - Encrypted RAR files.<br>  - Encrypted 7Z files.<br>  - TGZ files. <br>  - BZip and TBZ files. <br>2. Fixed the encoding issue when showing text files in foreign languages.<br>3. Fixed app crashing when opening certain documents.<br>4. Better handling of FaceID/TouchID to unlock screen."},{"version_id":"826957431","version_name":"15.50","version_date":"2018-05-08 18:25:47.000 +0800","version_description":"1. Added support for more compressed file types. Now iZip extracts:<br>  - Encrypted RAR files.<br>  - Encrypted 7Z files.<br>  - TGZ files. <br>  - BZip and TBZ files. <br>2. Fixed the encoding issue when showing text files in foreign languages.<br>3. Fixed app crashing when opening certain documents.<br>4. Better handling of FaceID/TouchID to unlock screen."},{"version_id":"826957431","version_name":"15.50","version_date":"2018-05-08 18:25:47.000 +0800","version_description":"1. Added support for more compressed file types. Now iZip extracts:<br>  - Encrypted RAR files.<br>  - Encrypted 7Z files.<br>  - TGZ files. <br>  - BZip and TBZ files. <br>2. Fixed the encoding issue when showing text files in foreign languages.<br>3. Fixed app crashing when opening certain documents.<br>4. Better handling of FaceID/TouchID to unlock screen."},{"version_id":"827212825","version_name":"15.51","version_date":"2018-05-20 01:41:45.000 +0800","version_description":"1. Updated library for GDPR compliance.<br>2. Bug fixes."},{"version_id":"827212825","version_name":"15.51","version_date":"2018-05-20 01:41:45.000 +0800","version_description":"1. Updated library for GDPR compliance.<br>2. Bug fixes."},{"version_id":"827212825","version_name":"15.51","version_date":"2018-05-20 01:41:45.000 +0800","version_description":"1. Updated library for GDPR compliance.<br>2. Bug fixes."},{"version_id":"827212825","version_name":"15.51","version_date":"2018-05-20 01:41:45.000 +0800","version_description":"1. Updated library for GDPR compliance.<br>2. Bug fixes."},{"version_id":"827212825","version_name":"15.51","version_date":"2018-05-20 01:41:45.000 +0800","version_description":"1. Updated library for GDPR compliance.<br>2. Bug fixes."},{"version_id":"827362494","version_name":"15.60","version_date":"2018-05-31 02:25:20.000 +0800","version_description":"1. Added support to open a document after being imported from Document Browser. Now document can be opened directly from Document Browser.<br>2. Added better error handling of unsupported document types."},{"version_id":"827362494","version_name":"15.60","version_date":"2018-05-31 02:25:20.000 +0800","version_description":"1. Added support to open a document after being imported from Document Browser. Now document can be opened directly from Document Browser.<br>2. Added better error handling of unsupported document types."},{"version_id":"827362494","version_name":"15.60","version_date":"2018-05-31 02:25:20.000 +0800","version_description":"1. Added support to open a document after being imported from Document Browser. Now document can be opened directly from Document Browser.<br>2. Added better error handling of unsupported document types."},{"version_id":"827362494","version_name":"15.60","version_date":"2018-05-31 02:25:20.000 +0800","version_description":"1. Added support to open a document after being imported from Document Browser. Now document can be opened directly from Document Browser.<br>2. Added better error handling of unsupported document types."},{"version_id":"827362494","version_name":"15.60","version_date":"2018-05-31 02:25:20.000 +0800","version_description":"1. Added support to open a document after being imported from Document Browser. Now document can be opened directly from Document Browser.<br>2. Added better error handling of unsupported document types."},{"version_id":"828116836","version_name":"18.01","version_date":"2018-11-18 22:50:14.000 +0800","version_description":"1.Fixed the defect when deleting a single file.<br>2.Fixed the icons of supported zip files."},{"version_id":"828116836","version_name":"16.0","version_date":"2018-08-05 02:38:29.000 +0800","version_description":"1. Added an option in Settings to convert HEIC images to JPG images.<br>2. Allow printing multiple documents and images.<br>3. Allow sharing multiple documents.<br>4. Added support of OneDrive for Business in Document Browser."},{"version_id":"828116836","version_name":"18.01","version_date":"2018-11-18 22:50:14.000 +0800","version_description":"1.Fixed the defect when deleting a single file.<br>2.Fixed the icons of supported zip files."},{"version_id":"828116836","version_name":"16.0","version_date":"2018-08-05 02:38:29.000 +0800","version_description":"1. Added an option in Settings to convert HEIC images to JPG images.<br>2. Allow printing multiple documents and images.<br>3. Allow sharing multiple documents.<br>4. Added support of OneDrive for Business in Document Browser."},{"version_id":"828116836","version_name":"18.01","version_date":"2018-11-18 22:50:14.000 +0800","version_description":"1.Fixed the defect when deleting a single file.<br>2.Fixed the icons of supported zip files."},{"version_id":"828116836","version_name":"16.0","version_date":"2018-08-05 02:38:29.000 +0800","version_description":"1. Added an option in Settings to convert HEIC images to JPG images.<br>2. Allow printing multiple documents and images.<br>3. Allow sharing multiple documents.<br>4. Added support of OneDrive for Business in Document Browser."},{"version_id":"828116836","version_name":"18.01","version_date":"2018-11-18 22:50:14.000 +0800","version_description":"1.Fixed the defect when deleting a single file.<br>2.Fixed the icons of supported zip files."},{"version_id":"828116836","version_name":"16.0","version_date":"2018-08-05 02:38:29.000 +0800","version_description":"1. Added an option in Settings to convert HEIC images to JPG images.<br>2. Allow printing multiple documents and images.<br>3. Allow sharing multiple documents.<br>4. Added support of OneDrive for Business in Document Browser."},{"version_id":"828116836","version_name":"18.01","version_date":"2018-11-18 22:50:14.000 +0800","version_description":"1.Fixed the defect when deleting a single file.<br>2.Fixed the icons of supported zip files."},{"version_id":"828116836","version_name":"16.0","version_date":"2018-08-05 02:38:29.000 +0800","version_description":"1. Added an option in Settings to convert HEIC images to JPG images.<br>2. Allow printing multiple documents and images.<br>3. Allow sharing multiple documents.<br>4. Added support of OneDrive for Business in Document Browser."},{"version_id":"828126123","version_name":"16.01","version_date":"2018-08-07 20:32:46.000 +0800","version_description":"1. Fixed the issue of compressing videos from Photo Library.<br>2. Optimized HEIC image processing."},{"version_id":"828126123","version_name":"16.01","version_date":"2018-08-07 20:32:46.000 +0800","version_description":"1. Fixed the issue of compressing videos from Photo Library.<br>2. Optimized HEIC image processing."},{"version_id":"828126123","version_name":"16.01","version_date":"2018-08-07 20:32:46.000 +0800","version_description":"1. Fixed the issue of compressing videos from Photo Library.<br>2. Optimized HEIC image processing."},{"version_id":"828126123","version_name":"16.01","version_date":"2018-08-07 20:32:46.000 +0800","version_description":"1. Fixed the issue of compressing videos from Photo Library.<br>2. Optimized HEIC image processing."},{"version_id":"828126123","version_name":"16.01","version_date":"2018-08-07 20:32:46.000 +0800","version_description":"1. Fixed the issue of compressing videos from Photo Library.<br>2. Optimized HEIC image processing."},{"version_id":"828278180","version_name":"16.03","version_date":"2018-08-19 18:57:27.000 +0800","version_description":"1. Updated libraries.<br>2. Fixed an issue of resulting in an empty HEIC image."},{"version_id":"828278180","version_name":"16.03","version_date":"2018-08-19 18:57:27.000 +0800","version_description":"1. Updated libraries.<br>2. Fixed an issue of resulting in an empty HEIC image."},{"version_id":"828278180","version_name":"16.03","version_date":"2018-08-19 18:57:27.000 +0800","version_description":"1. Updated libraries.<br>2. Fixed an issue of resulting in an empty HEIC image."},{"version_id":"828278180","version_name":"16.03","version_date":"2018-08-19 18:57:27.000 +0800","version_description":"1. Updated libraries.<br>2. Fixed an issue of resulting in an empty HEIC image."},{"version_id":"828278180","version_name":"16.03","version_date":"2018-08-19 18:57:27.000 +0800","version_description":"1. Updated libraries.<br>2. Fixed an issue of resulting in an empty HEIC image."},{"version_id":"828568850","version_name":"17.0","version_date":"2018-09-14 01:27:45.000 +0800","version_description":"1. Now supports to open a file directly from cloud drives by tapping on the file. <br>2. Added Default Sorting Method in Settings. Sorting can be done in both ascending and descending orders by tapping on the sorting method. Cloud drives are sorted using the same sorting method.<br>3. Added back In-app Upgrade in iZip free version. Now iZip users can upgrade through in-app purchase to the Premium version.<br>4. Added Spotlight search support for Files. Users now can search and open a file in iZip using Spotlight search.<br>5. Various bug fixed.<br>6. Build for iOS 12 and new iPhone devices."},{"version_id":"828568850","version_name":"17.0","version_date":"2018-09-14 01:27:45.000 +0800","version_description":"1. Now supports to open a file directly from cloud drives by tapping on the file. <br>2. Added Default Sorting Method in Settings. Sorting can be done in both ascending and descending orders by tapping on the sorting method. Cloud drives are sorted using the same sorting method.<br>3. Added back In-app Upgrade in iZip free version. Now iZip users can upgrade through in-app purchase to the Premium version.<br>4. Added Spotlight search support for Files. Users now can search and open a file in iZip using Spotlight search.<br>5. Various bug fixed.<br>6. Build for iOS 12 and new iPhone devices."},{"version_id":"828568850","version_name":"17.0","version_date":"2018-09-14 01:27:45.000 +0800","version_description":"1. Now supports to open a file directly from cloud drives by tapping on the file. <br>2. Added Default Sorting Method in Settings. Sorting can be done in both ascending and descending orders by tapping on the sorting method. Cloud drives are sorted using the same sorting method.<br>3. Added back In-app Upgrade in iZip free version. Now iZip users can upgrade through in-app purchase to the Premium version.<br>4. Added Spotlight search support for Files. Users now can search and open a file in iZip using Spotlight search.<br>5. Various bug fixed.<br>6. Build for iOS 12 and new iPhone devices."},{"version_id":"828568850","version_name":"17.0","version_date":"2018-09-14 01:27:45.000 +0800","version_description":"1. Now supports to open a file directly from cloud drives by tapping on the file. <br>2. Added Default Sorting Method in Settings. Sorting can be done in both ascending and descending orders by tapping on the sorting method. Cloud drives are sorted using the same sorting method.<br>3. Added back In-app Upgrade in iZip free version. Now iZip users can upgrade through in-app purchase to the Premium version.<br>4. Added Spotlight search support for Files. Users now can search and open a file in iZip using Spotlight search.<br>5. Various bug fixed.<br>6. Build for iOS 12 and new iPhone devices."},{"version_id":"828568850","version_name":"17.0","version_date":"2018-09-14 01:27:45.000 +0800","version_description":"1. Now supports to open a file directly from cloud drives by tapping on the file. <br>2. Added Default Sorting Method in Settings. Sorting can be done in both ascending and descending orders by tapping on the sorting method. Cloud drives are sorted using the same sorting method.<br>3. Added back In-app Upgrade in iZip free version. Now iZip users can upgrade through in-app purchase to the Premium version.<br>4. Added Spotlight search support for Files. Users now can search and open a file in iZip using Spotlight search.<br>5. Various bug fixed.<br>6. Build for iOS 12 and new iPhone devices."},{"version_id":"829269172","version_name":"18.0","version_date":"2018-11-15 14:30:20.000 +0800","version_description":"1. Added support of extracting more file formats including: ISO, DEB, CAB, Split RAR, JAR, RPM, CBZ, etc..<br>2. Added Landscape mode on iPhone devices.<br>3. Added storage space information in Data Statistics.<br>4. Built for new iPad Pro devices.<br>5. Optimized photo compressing.<br>6. Other bug fixes."},{"version_id":"829269172","version_name":"18.0","version_date":"2018-11-15 14:30:20.000 +0800","version_description":"1. Added support of extracting more file formats including: ISO, DEB, CAB, Split RAR, JAR, RPM, CBZ, etc..<br>2. Added Landscape mode on iPhone devices.<br>3. Added storage space information in Data Statistics.<br>4. Built for new iPad Pro devices.<br>5. Optimized photo compressing.<br>6. Other bug fixes."},{"version_id":"829269172","version_name":"18.0","version_date":"2018-11-15 14:30:20.000 +0800","version_description":"1. Added support of extracting more file formats including: ISO, DEB, CAB, Split RAR, JAR, RPM, CBZ, etc..<br>2. Added Landscape mode on iPhone devices.<br>3. Added storage space information in Data Statistics.<br>4. Built for new iPad Pro devices.<br>5. Optimized photo compressing.<br>6. Other bug fixes."},{"version_id":"829269172","version_name":"18.0","version_date":"2018-11-15 14:30:20.000 +0800","version_description":"1. Added support of extracting more file formats including: ISO, DEB, CAB, Split RAR, JAR, RPM, CBZ, etc..<br>2. Added Landscape mode on iPhone devices.<br>3. Added storage space information in Data Statistics.<br>4. Built for new iPad Pro devices.<br>5. Optimized photo compressing.<br>6. Other bug fixes."},{"version_id":"829269172","version_name":"18.0","version_date":"2018-11-15 14:30:20.000 +0800","version_description":"1. Added support of extracting more file formats including: ISO, DEB, CAB, Split RAR, JAR, RPM, CBZ, etc..<br>2. Added Landscape mode on iPhone devices.<br>3. Added storage space information in Data Statistics.<br>4. Built for new iPad Pro devices.<br>5. Optimized photo compressing.<br>6. Other bug fixes."},{"version_id":"829333303","version_name":"18.01","version_date":"2018-11-18 22:50:14.000 +0800","version_description":"1.Fixed the defect when deleting a single file.<br>2.Fixed the icons of supported zip files."},{"version_id":"829333303","version_name":"18.01","version_date":"2018-11-18 22:50:14.000 +0800","version_description":"1.Fixed the defect when deleting a single file.<br>2.Fixed the icons of supported zip files."},{"version_id":"829333303","version_name":"18.01","version_date":"2018-11-18 22:50:14.000 +0800","version_description":"1.Fixed the defect when deleting a single file.<br>2.Fixed the icons of supported zip files."},{"version_id":"829333303","version_name":"18.01","version_date":"2018-11-18 22:50:14.000 +0800","version_description":"1.Fixed the defect when deleting a single file.<br>2.Fixed the icons of supported zip files."},{"version_id":"829333303","version_name":"18.01","version_date":"2018-11-18 22:50:14.000 +0800","version_description":"1.Fixed the defect when deleting a single file.<br>2.Fixed the icons of supported zip files."},{"version_id":"829982237","version_name":"18.50","version_date":"2019-02-01 11:43:36.000 +0800","version_description":"1. Added more languages. Now iZip supports the following languages: English, Chinese, Spanish, French, Japanese,  Russian, Germany, Portuguese, Arabic.<br>2. Fixed defects."},{"version_id":"829982237","version_name":"18.50","version_date":"2019-02-01 11:43:36.000 +0800","version_description":"1. Added more languages. Now iZip supports the following languages: English, Chinese, Spanish, French, Japanese,  Russian, Germany, Portuguese, Arabic.<br>2. Fixed defects."},{"version_id":"829982237","version_name":"18.50","version_date":"2019-02-01 11:43:36.000 +0800","version_description":"1. Added more languages. Now iZip supports the following languages: English, Chinese, Spanish, French, Japanese,  Russian, Germany, Portuguese, Arabic.<br>2. Fixed defects."},{"version_id":"829982237","version_name":"18.50","version_date":"2019-02-01 11:43:36.000 +0800","version_description":"1. Added more languages. Now iZip supports the following languages: English, Chinese, Spanish, French, Japanese,  Russian, Germany, Portuguese, Arabic.<br>2. Fixed defects."},{"version_id":"829982237","version_name":"18.50","version_date":"2019-02-01 11:43:36.000 +0800","version_description":"1. Added more languages. Now iZip supports the following languages: English, Chinese, Spanish, French, Japanese,  Russian, Germany, Portuguese, Arabic.<br>2. Fixed defects."},{"version_id":"831418759","version_name":"18.51","version_date":"2019-05-24 01:08:14.000 +0800","version_description":"Fixed defects."},{"version_id":"831418759","version_name":"18.51","version_date":"2019-05-24 01:08:14.000 +0800","version_description":"Fixed defects."},{"version_id":"831418759","version_name":"18.51","version_date":"2019-05-24 01:08:14.000 +0800","version_description":"Fixed defects."},{"version_id":"831418759","version_name":"18.51","version_date":"2019-05-24 01:08:14.000 +0800","version_description":"Fixed defects."},{"version_id":"831418759","version_name":"18.51","version_date":"2019-05-24 01:08:14.000 +0800","version_description":"Fixed defects."},{"version_id":"832302803","version_name":"18.52","version_date":"2019-08-09 01:49:15.000 +0800","version_description":"Fixed defects."},{"version_id":"832302803","version_name":"18.52","version_date":"2019-08-09 01:49:15.000 +0800","version_description":"Fixed defects."},{"version_id":"832302803","version_name":"18.52","version_date":"2019-08-09 01:49:15.000 +0800","version_description":"Fixed defects."},{"version_id":"832302803","version_name":"18.52","version_date":"2019-08-09 01:49:15.000 +0800","version_description":"Fixed defects."},{"version_id":"832302803","version_name":"18.52","version_date":"2019-08-09 01:49:15.000 +0800","version_description":"Fixed defects."},{"version_id":"832875367","version_name":"18.60","version_date":"2019-09-25 18:59:17.000 +0800","version_description":"Fixed defects when running on iOS 13."},{"version_id":"832875367","version_name":"18.60","version_date":"2019-09-25 18:59:17.000 +0800","version_description":"Fixed defects when running on iOS 13."},{"version_id":"832875367","version_name":"18.60","version_date":"2019-09-25 18:59:17.000 +0800","version_description":"Fixed defects when running on iOS 13."},{"version_id":"832875367","version_name":"18.60","version_date":"2019-09-25 18:59:17.000 +0800","version_description":"Fixed defects when running on iOS 13."},{"version_id":"832875367","version_name":"18.60","version_date":"2019-09-25 18:59:17.000 +0800","version_description":"Fixed defects when running on iOS 13."},{"version_id":"833016443","version_name":"18.61","version_date":"2019-10-03 01:08:27.000 +0800","version_description":"Fixed defects."},{"version_id":"833016443","version_name":"18.61","version_date":"2019-10-03 01:08:27.000 +0800","version_description":"Fixed defects."},{"version_id":"833016443","version_name":"18.61","version_date":"2019-10-03 01:08:27.000 +0800","version_description":"Fixed defects."},{"version_id":"833016443","version_name":"18.61","version_date":"2019-10-03 01:08:27.000 +0800","version_description":"Fixed defects."},{"version_id":"833016443","version_name":"18.61","version_date":"2019-10-03 01:08:27.000 +0800","version_description":"Fixed defects."},{"version_id":"833044908","version_name":"18.62","version_date":"2019-10-07 15:38:56.000 +0800","version_description":"Fixed banner ads defect."},{"version_id":"833044908","version_name":"18.62","version_date":"2019-10-07 15:38:56.000 +0800","version_description":"Fixed banner ads defect."},{"version_id":"833044908","version_name":"18.62","version_date":"2019-10-07 15:38:56.000 +0800","version_description":"Fixed banner ads defect."},{"version_id":"833044908","version_name":"18.62","version_date":"2019-10-07 15:38:56.000 +0800","version_description":"Fixed banner ads defect."},{"version_id":"833044908","version_name":"18.62","version_date":"2019-10-07 15:38:56.000 +0800","version_description":"Fixed banner ads defect."},{"version_id":"833137015","version_name":"18.70","version_date":"2019-10-12 12:39:34.000 +0800","version_description":"Fixed defects."},{"version_id":"833137015","version_name":"18.70","version_date":"2019-10-12 12:39:34.000 +0800","version_description":"Fixed defects."},{"version_id":"833137015","version_name":"18.70","version_date":"2019-10-12 12:39:34.000 +0800","version_description":"Fixed defects."},{"version_id":"833137015","version_name":"18.70","version_date":"2019-10-12 12:39:34.000 +0800","version_description":"Fixed defects."},{"version_id":"833137015","version_name":"18.70","version_date":"2019-10-12 12:39:34.000 +0800","version_description":"Fixed defects."},{"version_id":"833388374","version_name":"18.71","version_date":"2019-10-30 12:47:53.000 +0800","version_description":"Fixed defects."},{"version_id":"833388374","version_name":"18.71","version_date":"2019-10-30 12:47:53.000 +0800","version_description":"Fixed defects."},{"version_id":"833388374","version_name":"18.71","version_date":"2019-10-30 12:47:53.000 +0800","version_description":"Fixed defects."},{"version_id":"833388374","version_name":"18.71","version_date":"2019-10-30 12:47:53.000 +0800","version_description":"Fixed defects."},{"version_id":"833388374","version_name":"18.71","version_date":"2019-10-30 12:47:53.000 +0800","version_description":"Fixed defects."},{"version_id":"833401063","version_name":"18.72","version_date":"2019-10-30 19:32:01.000 +0800","version_description":"Fixed a defect which causes the App to crash when opening a file in iZip from another App."},{"version_id":"833401063","version_name":"18.72","version_date":"2019-10-30 19:32:01.000 +0800","version_description":"Fixed a defect which causes the App to crash when opening a file in iZip from another App."},{"version_id":"833401063","version_name":"18.72","version_date":"2019-10-30 19:32:01.000 +0800","version_description":"Fixed a defect which causes the App to crash when opening a file in iZip from another App."},{"version_id":"833401063","version_name":"18.72","version_date":"2019-10-30 19:32:01.000 +0800","version_description":"Fixed a defect which causes the App to crash when opening a file in iZip from another App."},{"version_id":"833401063","version_name":"18.72","version_date":"2019-10-30 19:32:01.000 +0800","version_description":"Fixed a defect which causes the App to crash when opening a file in iZip from another App."},{"version_id":"833891471","version_name":"18.73","version_date":"2019-12-06 01:14:15.000 +0800","version_description":"Fixed defects."},{"version_id":"833891471","version_name":"18.73","version_date":"2019-12-06 01:14:15.000 +0800","version_description":"Fixed defects."},{"version_id":"833891471","version_name":"18.73","version_date":"2019-12-06 01:14:15.000 +0800","version_description":"Fixed defects."},{"version_id":"833891471","version_name":"18.73","version_date":"2019-12-06 01:14:15.000 +0800","version_description":"Fixed defects."},{"version_id":"833891471","version_name":"18.73","version_date":"2019-12-06 01:14:15.000 +0800","version_description":"Fixed defects."},{"version_id":"834897033","version_name":"18.76","version_date":"2020-03-22 15:34:20.000 +0800","version_description":"Fixed defects."},{"version_id":"834897033","version_name":"18.74","version_date":"2020-02-29 00:54:56.000 +0800","version_description":"1.Fixed App crashing when logging into Box.<br>2.Added support to share folders without zipping them first.<br>3.Fixed other defects."},{"version_id":"834897033","version_name":"18.76","version_date":"2020-03-22 15:34:20.000 +0800","version_description":"Fixed defects."},{"version_id":"834897033","version_name":"18.74","version_date":"2020-02-29 00:54:56.000 +0800","version_description":"1.Fixed App crashing when logging into Box.<br>2.Added support to share folders without zipping them first.<br>3.Fixed other defects."},{"version_id":"834897033","version_name":"18.76","version_date":"2020-03-22 15:34:20.000 +0800","version_description":"Fixed defects."},{"version_id":"834897033","version_name":"18.74","version_date":"2020-02-29 00:54:56.000 +0800","version_description":"1.Fixed App crashing when logging into Box.<br>2.Added support to share folders without zipping them first.<br>3.Fixed other defects."},{"version_id":"834897033","version_name":"18.76","version_date":"2020-03-22 15:34:20.000 +0800","version_description":"Fixed defects."},{"version_id":"834897033","version_name":"18.74","version_date":"2020-02-29 00:54:56.000 +0800","version_description":"1.Fixed App crashing when logging into Box.<br>2.Added support to share folders without zipping them first.<br>3.Fixed other defects."},{"version_id":"834897033","version_name":"18.76","version_date":"2020-03-22 15:34:20.000 +0800","version_description":"Fixed defects."},{"version_id":"834897033","version_name":"18.74","version_date":"2020-02-29 00:54:56.000 +0800","version_description":"1.Fixed App crashing when logging into Box.<br>2.Added support to share folders without zipping them first.<br>3.Fixed other defects."},{"version_id":"835198239","version_name":"18.75","version_date":"2020-03-20 22:09:37.000 +0800","version_description":"Fixed defects."},{"version_id":"835198239","version_name":"18.75","version_date":"2020-03-20 22:09:37.000 +0800","version_description":"Fixed defects."},{"version_id":"835198239","version_name":"18.75","version_date":"2020-03-20 22:09:37.000 +0800","version_description":"Fixed defects."},{"version_id":"835198239","version_name":"18.75","version_date":"2020-03-20 22:09:37.000 +0800","version_description":"Fixed defects."},{"version_id":"835198239","version_name":"18.75","version_date":"2020-03-20 22:09:37.000 +0800","version_description":"Fixed defects."},{"version_id":"835214481","version_name":"18.76","version_date":"2020-03-22 15:34:20.000 +0800","version_description":"Fixed defects."},{"version_id":"835214481","version_name":"18.76","version_date":"2020-03-22 15:34:20.000 +0800","version_description":"Fixed defects."},{"version_id":"835214481","version_name":"18.76","version_date":"2020-03-22 15:34:20.000 +0800","version_description":"Fixed defects."},{"version_id":"835214481","version_name":"18.76","version_date":"2020-03-22 15:34:20.000 +0800","version_description":"Fixed defects."},{"version_id":"835214481","version_name":"18.76","version_date":"2020-03-22 15:34:20.000 +0800","version_description":"Fixed defects."},{"version_id":"835672595","version_name":"18.77","version_date":"2020-04-24 14:17:32.000 +0800","version_description":"Fixed defects."},{"version_id":"835672595","version_name":"18.77","version_date":"2020-04-24 14:17:32.000 +0800","version_description":"Fixed defects."},{"version_id":"835672595","version_name":"18.77","version_date":"2020-04-24 14:17:32.000 +0800","version_description":"Fixed defects."},{"version_id":"835672595","version_name":"18.77","version_date":"2020-04-24 14:17:32.000 +0800","version_description":"Fixed defects."},{"version_id":"835672595","version_name":"18.77","version_date":"2020-04-24 14:17:32.000 +0800","version_description":"Fixed defects."},{"version_id":"835988773","version_name":"18.78","version_date":"2020-05-17 15:19:29.000 +0800","version_description":"1.Fixed issues when playing mp4 videos and wav files.<br>2.Removed Open in and Save buttons in Files. <br>3.Improved Transfer Files from iZip to iZip Pro.<br>4.Fixed other defects."},{"version_id":"835988773","version_name":"18.78","version_date":"2020-05-17 15:19:29.000 +0800","version_description":"1.Fixed issues when playing mp4 videos and wav files.<br>2.Removed Open in and Save buttons in Files. <br>3.Improved Transfer Files from iZip to iZip Pro.<br>4.Fixed other defects."},{"version_id":"835988773","version_name":"18.78","version_date":"2020-05-17 15:19:29.000 +0800","version_description":"1.Fixed issues when playing mp4 videos and wav files.<br>2.Removed Open in and Save buttons in Files. <br>3.Improved Transfer Files from iZip to iZip Pro.<br>4.Fixed other defects."},{"version_id":"835988773","version_name":"18.78","version_date":"2020-05-17 15:19:29.000 +0800","version_description":"1.Fixed issues when playing mp4 videos and wav files.<br>2.Removed Open in and Save buttons in Files. <br>3.Improved Transfer Files from iZip to iZip Pro.<br>4.Fixed other defects."},{"version_id":"835988773","version_name":"18.78","version_date":"2020-05-17 15:19:29.000 +0800","version_description":"1.Fixed issues when playing mp4 videos and wav files.<br>2.Removed Open in and Save buttons in Files. <br>3.Improved Transfer Files from iZip to iZip Pro.<br>4.Fixed other defects."},{"version_id":"836009415","version_name":"18.79","version_date":"2020-05-19 13:12:39.000 +0800","version_description":"1. Fixed the issue of using Touch ID to unlock screen.<br>2. Added Save button back in Files."},{"version_id":"836009415","version_name":"18.79","version_date":"2020-05-19 13:12:39.000 +0800","version_description":"1. Fixed the issue of using Touch ID to unlock screen.<br>2. Added Save button back in Files."},{"version_id":"836009415","version_name":"18.79","version_date":"2020-05-19 13:12:39.000 +0800","version_description":"1. Fixed the issue of using Touch ID to unlock screen.<br>2. Added Save button back in Files."},{"version_id":"836009415","version_name":"18.79","version_date":"2020-05-19 13:12:39.000 +0800","version_description":"1. Fixed the issue of using Touch ID to unlock screen.<br>2. Added Save button back in Files."},{"version_id":"836009415","version_name":"18.79","version_date":"2020-05-19 13:12:39.000 +0800","version_description":"1. Fixed the issue of using Touch ID to unlock screen.<br>2. Added Save button back in Files."},{"version_id":"836089216","version_name":"18.79","version_date":"2020-05-19 13:12:39.000 +0800","version_description":"1. Fixed the issue of using Touch ID to unlock screen.<br>2. Added Save button back in Files."},{"version_id":"836089216","version_name":"18.79","version_date":"2020-05-19 13:12:39.000 +0800","version_description":"1. Fixed the issue of using Touch ID to unlock screen.<br>2. Added Save button back in Files."},{"version_id":"836089216","version_name":"18.79","version_date":"2020-05-19 13:12:39.000 +0800","version_description":"1. Fixed the issue of using Touch ID to unlock screen.<br>2. Added Save button back in Files."},{"version_id":"836089216","version_name":"18.79","version_date":"2020-05-19 13:12:39.000 +0800","version_description":"1. Fixed the issue of using Touch ID to unlock screen.<br>2. Added Save button back in Files."},{"version_id":"836089216","version_name":"18.79","version_date":"2020-05-19 13:12:39.000 +0800","version_description":"1. Fixed the issue of using Touch ID to unlock screen.<br>2. Added Save button back in Files."},{"version_id":"836143873","version_name":"18.80","version_date":"2020-05-27 02:22:49.000 +0800","version_description":"Fixed app crashing when opening certain file types."},{"version_id":"836143873","version_name":"18.80","version_date":"2020-05-27 02:22:49.000 +0800","version_description":"Fixed app crashing when opening certain file types."},{"version_id":"836143873","version_name":"18.80","version_date":"2020-05-27 02:22:49.000 +0800","version_description":"Fixed app crashing when opening certain file types."},{"version_id":"836143873","version_name":"18.80","version_date":"2020-05-27 02:22:49.000 +0800","version_description":"Fixed app crashing when opening certain file types."},{"version_id":"836143873","version_name":"18.80","version_date":"2020-05-27 02:22:49.000 +0800","version_description":"Fixed app crashing when opening certain file types."},{"version_id":"836182539","version_name":"18.81","version_date":"2020-05-29 11:50:31.000 +0800","version_description":"Fixed an issue of opening certain files when running on iOS11 and iOS 12."},{"version_id":"836182539","version_name":"18.81","version_date":"2020-05-29 11:50:31.000 +0800","version_description":"Fixed an issue of opening certain files when running on iOS11 and iOS 12."},{"version_id":"836182539","version_name":"18.81","version_date":"2020-05-29 11:50:31.000 +0800","version_description":"Fixed an issue of opening certain files when running on iOS11 and iOS 12."},{"version_id":"836182539","version_name":"18.81","version_date":"2020-05-29 11:50:31.000 +0800","version_description":"Fixed an issue of opening certain files when running on iOS11 and iOS 12."},{"version_id":"836182539","version_name":"18.81","version_date":"2020-05-29 11:50:31.000 +0800","version_description":"Fixed an issue of opening certain files when running on iOS11 and iOS 12."},{"version_id":"836398658","version_name":"18.82","version_date":"2020-06-13 18:47:10.000 +0800","version_description":"1.Improved handling of opening unsupported file types.<br>2.Fixed other issues."},{"version_id":"836398658","version_name":"18.82","version_date":"2020-06-13 18:47:10.000 +0800","version_description":"1.Improved handling of opening unsupported file types.<br>2.Fixed other issues."},{"version_id":"836398658","version_name":"18.82","version_date":"2020-06-13 18:47:10.000 +0800","version_description":"1.Improved handling of opening unsupported file types.<br>2.Fixed other issues."},{"version_id":"836398658","version_name":"18.82","version_date":"2020-06-13 18:47:10.000 +0800","version_description":"1.Improved handling of opening unsupported file types.<br>2.Fixed other issues."},{"version_id":"836398658","version_name":"18.82","version_date":"2020-06-13 18:47:10.000 +0800","version_description":"1.Improved handling of opening unsupported file types.<br>2.Fixed other issues."},{"version_id":"837857971","version_name":"19.0","version_date":"2020-09-19 16:39:35.000 +0800","version_description":"1.Build for iOS 14.<br>2.Now supports dark mode.<br>3.Fixed defects."},{"version_id":"837857971","version_name":"19.0","version_date":"2020-09-19 16:39:35.000 +0800","version_description":"1.Build for iOS 14.<br>2.Now supports dark mode.<br>3.Fixed defects."},{"version_id":"837857971","version_name":"19.0","version_date":"2020-09-19 16:39:35.000 +0800","version_description":"1.Build for iOS 14.<br>2.Now supports dark mode.<br>3.Fixed defects."},{"version_id":"837857971","version_name":"19.0","version_date":"2020-09-19 16:39:35.000 +0800","version_description":"1.Build for iOS 14.<br>2.Now supports dark mode.<br>3.Fixed defects."},{"version_id":"837857971","version_name":"19.0","version_date":"2020-09-19 16:39:35.000 +0800","version_description":"1.Build for iOS 14.<br>2.Now supports dark mode.<br>3.Fixed defects."},{"version_id":"838318329","version_name":"19.02","version_date":"2020-10-22 21:19:41.000 +0800","version_description":"Fixed defects."},{"version_id":"838318329","version_name":"19.02","version_date":"2020-10-22 21:19:41.000 +0800","version_description":"Fixed defects."},{"version_id":"838318329","version_name":"19.02","version_date":"2020-10-22 21:19:41.000 +0800","version_description":"Fixed defects."},{"version_id":"838318329","version_name":"19.02","version_date":"2020-10-22 21:19:41.000 +0800","version_description":"Fixed defects."},{"version_id":"838318329","version_name":"19.02","version_date":"2020-10-22 21:19:41.000 +0800","version_description":"Fixed defects."},{"version_id":"838368665","version_name":"19.03","version_date":"2020-10-26 01:17:00.000 +0800","version_description":"Fixed defects."},{"version_id":"838368665","version_name":"19.03","version_date":"2020-10-26 01:17:00.000 +0800","version_description":"Fixed defects."},{"version_id":"838368665","version_name":"19.03","version_date":"2020-10-26 01:17:00.000 +0800","version_description":"Fixed defects."},{"version_id":"838368665","version_name":"19.03","version_date":"2020-10-26 01:17:00.000 +0800","version_description":"Fixed defects."},{"version_id":"838368665","version_name":"19.03","version_date":"2020-10-26 01:17:00.000 +0800","version_description":"Fixed defects."},{"version_id":"838421259","version_name":"19.04","version_date":"2020-10-28 18:09:01.000 +0800","version_description":"Fixed defects."},{"version_id":"838421259","version_name":"19.04","version_date":"2020-10-28 18:09:01.000 +0800","version_description":"Fixed defects."},{"version_id":"838421259","version_name":"19.04","version_date":"2020-10-28 18:09:01.000 +0800","version_description":"Fixed defects."},{"version_id":"838421259","version_name":"19.04","version_date":"2020-10-28 18:09:01.000 +0800","version_description":"Fixed defects."},{"version_id":"838421259","version_name":"19.04","version_date":"2020-10-28 18:09:01.000 +0800","version_description":"Fixed defects."},{"version_id":"838522568","version_name":"19.06","version_date":"2020-11-04 18:05:32.000 +0800","version_description":"Fixed defects."},{"version_id":"838522568","version_name":"19.06","version_date":"2020-11-04 18:05:32.000 +0800","version_description":"Fixed defects."},{"version_id":"838522568","version_name":"19.06","version_date":"2020-11-04 18:05:32.000 +0800","version_description":"Fixed defects."},{"version_id":"838522568","version_name":"19.06","version_date":"2020-11-04 18:05:32.000 +0800","version_description":"Fixed defects."},{"version_id":"838522568","version_name":"19.06","version_date":"2020-11-04 18:05:32.000 +0800","version_description":"Fixed defects."},{"version_id":"839046567","version_name":"19.08","version_date":"2020-11-12 17:55:12.000 +0800","version_description":"Fixed defects."},{"version_id":"839046567","version_name":"19.08","version_date":"2020-11-12 17:55:12.000 +0800","version_description":"Fixed defects."},{"version_id":"839046567","version_name":"19.08","version_date":"2020-11-12 17:55:12.000 +0800","version_description":"Fixed defects."},{"version_id":"839046567","version_name":"19.08","version_date":"2020-11-12 17:55:12.000 +0800","version_description":"Fixed defects."},{"version_id":"839046567","version_name":"19.08","version_date":"2020-11-12 17:55:12.000 +0800","version_description":"Fixed defects."},{"version_id":"840642975","version_name":"19.10","version_date":"2021-03-09 20:49:03.000 +0800","version_description":"Fixed defects."},{"version_id":"840642975","version_name":"19.10","version_date":"2021-03-09 20:49:03.000 +0800","version_description":"Fixed defects."},{"version_id":"840642975","version_name":"19.10","version_date":"2021-03-09 20:49:03.000 +0800","version_description":"Fixed defects."},{"version_id":"840642975","version_name":"19.10","version_date":"2021-03-09 20:49:03.000 +0800","version_description":"Fixed defects."},{"version_id":"840642975","version_name":"19.10","version_date":"2021-03-09 20:49:03.000 +0800","version_description":"Fixed defects."},{"version_id":"840837083","version_name":"19.11","version_date":"2021-03-12 12:59:56.000 +0800","version_description":"Fixed defects."},{"version_id":"840837083","version_name":"19.11","version_date":"2021-03-12 12:59:56.000 +0800","version_description":"Fixed defects."},{"version_id":"840837083","version_name":"19.11","version_date":"2021-03-12 12:59:56.000 +0800","version_description":"Fixed defects."},{"version_id":"840837083","version_name":"19.11","version_date":"2021-03-12 12:59:56.000 +0800","version_description":"Fixed defects."},{"version_id":"840837083","version_name":"19.11","version_date":"2021-03-12 12:59:56.000 +0800","version_description":"Fixed defects."},{"version_id":"841297570","version_name":"19.50","version_date":"2021-04-10 16:44:59.000 +0800","version_description":"Fixed defects."},{"version_id":"841297570","version_name":"19.50","version_date":"2021-04-10 16:44:59.000 +0800","version_description":"Fixed defects."},{"version_id":"841297570","version_name":"19.50","version_date":"2021-04-10 16:44:59.000 +0800","version_description":"Fixed defects."},{"version_id":"841297570","version_name":"19.50","version_date":"2021-04-10 16:44:59.000 +0800","version_description":"Fixed defects."},{"version_id":"841297570","version_name":"19.50","version_date":"2021-04-10 16:44:59.000 +0800","version_description":"Fixed defects."},{"version_id":"841434789","version_name":"19.51","version_date":"2021-04-16 10:33:57.000 +0800","version_description":"Fixed defects."},{"version_id":"841434789","version_name":"19.51","version_date":"2021-04-16 10:33:57.000 +0800","version_description":"Fixed defects."},{"version_id":"841434789","version_name":"19.51","version_date":"2021-04-16 10:33:57.000 +0800","version_description":"Fixed defects."},{"version_id":"841434789","version_name":"19.51","version_date":"2021-04-16 10:33:57.000 +0800","version_description":"Fixed defects."},{"version_id":"841434789","version_name":"19.51","version_date":"2021-04-16 10:33:57.000 +0800","version_description":"Fixed defects."},{"version_id":"842013330","version_name":"19.52","version_date":"2021-04-30 14:16:13.000 +0800","version_description":"Fixed defects."},{"version_id":"842013330","version_name":"19.52","version_date":"2021-04-30 14:16:13.000 +0800","version_description":"Fixed defects."},{"version_id":"842013330","version_name":"19.52","version_date":"2021-04-30 14:16:13.000 +0800","version_description":"Fixed defects."},{"version_id":"842013330","version_name":"19.52","version_date":"2021-04-30 14:16:13.000 +0800","version_description":"Fixed defects."},{"version_id":"842013330","version_name":"19.52","version_date":"2021-04-30 14:16:13.000 +0800","version_description":"Fixed defects."},{"version_id":"842876515","version_name":"19.54","version_date":"2021-07-04 14:15:17.000 +0800","version_description":"Fixed defects."},{"version_id":"842876515","version_name":"19.54","version_date":"2021-07-04 14:15:17.000 +0800","version_description":"Fixed defects."},{"version_id":"842876515","version_name":"19.54","version_date":"2021-07-04 14:15:17.000 +0800","version_description":"Fixed defects."},{"version_id":"842876515","version_name":"19.54","version_date":"2021-07-04 14:15:17.000 +0800","version_description":"Fixed defects."},{"version_id":"842876515","version_name":"19.54","version_date":"2021-07-04 14:15:17.000 +0800","version_description":"Fixed defects."}]