[{"version_id":"14940748","version_name":"1.0.0","version_date":"","version_description":""},{"version_id":"15066809","version_name":"1.0.1","version_date":"","version_description":""},{"version_id":"15156131","version_name":"1.0.2","version_date":"","version_description":""},{"version_id":"15450652","version_name":"1.0.3","version_date":"","version_description":""},{"version_id":"15713431","version_name":"1.1","version_date":"","version_description":""},{"version_id":"16053042","version_name":"1.2","version_date":"","version_description":""},{"version_id":"21752645","version_name":"1.2.2","version_date":"","version_description":""},{"version_id":"224702631","version_name":"1.5","version_date":"","version_description":""},{"version_id":"254462815","version_name":"1.5.1","version_date":"","version_description":""},{"version_id":"386722632","version_name":"1.5.2","version_date":"","version_description":""},{"version_id":"542682645","version_name":"1.5.3","version_date":"","version_description":""},{"version_id":"566723361","version_name":"1.5.4","version_date":"","version_description":""},{"version_id":"582212671","version_name":"1.5.5","version_date":"","version_description":""},{"version_id":"634972657","version_name":"1.5.6","version_date":"","version_description":""},{"version_id":"652403132","version_name":"1.5.7","version_date":"","version_description":""},{"version_id":"660832653","version_name":"1.5.8","version_date":"","version_description":""},{"version_id":"706352694","version_name":"1.6.0","version_date":"","version_description":""},{"version_id":"716663221","version_name":"1.6.1","version_date":"","version_description":""},{"version_id":"729552705","version_name":"1.6.2","version_date":"","version_description":""},{"version_id":"763392671","version_name":"1.6.3","version_date":"","version_description":""},{"version_id":"772612734","version_name":"1.6.4","version_date":"","version_description":""},{"version_id":"811265566","version_name":"1.6.5","version_date":"","version_description":""},{"version_id":"811614544","version_name":"1.6.6","version_date":"","version_description":""},{"version_id":"811664233","version_name":"1.6.6","version_date":"","version_description":""},{"version_id":"811742535","version_name":"1.6.7","version_date":"","version_description":""},{"version_id":"811834301","version_name":"1.6.8","version_date":"","version_description":""},{"version_id":"812056527","version_name":"1.6.9","version_date":"","version_description":""},{"version_id":"812213363","version_name":"1.7.0","version_date":"","version_description":""},{"version_id":"812290311","version_name":"1.7.1","version_date":"","version_description":""},{"version_id":"813101870","version_name":"1.8.0","version_date":"","version_description":""},{"version_id":"813150479","version_name":"1.8.1","version_date":"","version_description":""},{"version_id":"813204053","version_name":"1.8.2","version_date":"","version_description":""},{"version_id":"813556216","version_name":"1.9.0","version_date":"","version_description":""},{"version_id":"813639799","version_name":"1.9.0","version_date":"","version_description":""},{"version_id":"813725820","version_name":"1.9.0","version_date":"","version_description":""},{"version_id":"814192005","version_name":"1.9.1","version_date":"","version_description":""},{"version_id":"816620640","version_name":"1.9.2","version_date":"","version_description":""},{"version_id":"816751631","version_name":"1.9.3","version_date":"","version_description":""},{"version_id":"817352219","version_name":"1.9.4","version_date":"","version_description":""},{"version_id":"817943474","version_name":"1.9.5","version_date":"","version_description":""},{"version_id":"818060147","version_name":"1.9.6","version_date":"","version_description":""},{"version_id":"818130340","version_name":"1.10.0","version_date":"","version_description":""},{"version_id":"819666565","version_name":"1.10.1","version_date":"","version_description":""},{"version_id":"820633805","version_name":"1.11.0","version_date":"","version_description":""},{"version_id":"820818199","version_name":"1.11.1","version_date":"","version_description":""},{"version_id":"821182716","version_name":"1.11.2","version_date":"","version_description":""},{"version_id":"821358810","version_name":"1.11.3","version_date":"","version_description":""},{"version_id":"822713051","version_name":"1.11.4","version_date":"","version_description":""},{"version_id":"822860718","version_name":"1.12.0","version_date":"","version_description":""},{"version_id":"823249623","version_name":"1.12.1","version_date":"","version_description":""},{"version_id":"823359437","version_name":"1.12.2","version_date":"","version_description":""},{"version_id":"825215015","version_name":"1.13.0","version_date":"","version_description":""},{"version_id":"825353920","version_name":"1.13.1","version_date":"","version_description":""},{"version_id":"825602815","version_name":"1.14.0","version_date":"","version_description":""},{"version_id":"825995858","version_name":"1.15.0","version_date":"","version_description":""},{"version_id":"826411892","version_name":"1.16.0","version_date":"","version_description":""},{"version_id":"826723862","version_name":"1.17.0","version_date":"","version_description":""},{"version_id":"827253336","version_name":"1.18.0","version_date":"","version_description":""},{"version_id":"827980019","version_name":"1.23.0","version_date":"","version_description":""},{"version_id":"827980019","version_name":"1.21.0","version_date":"","version_description":""},{"version_id":"827980019","version_name":"1.19.0","version_date":"","version_description":""},{"version_id":"827980019","version_name":"1.22.1","version_date":"","version_description":""},{"version_id":"829328191","version_name":"1.20.0","version_date":"","version_description":""},{"version_id":"829469698","version_name":"1.20.1","version_date":"","version_description":""},{"version_id":"829914634","version_name":"1.21.0","version_date":"","version_description":""},{"version_id":"830137602","version_name":"1.22.0","version_date":"","version_description":""},{"version_id":"830352239","version_name":"1.22.1","version_date":"","version_description":""},{"version_id":"830884338","version_name":"1.23.0","version_date":"","version_description":""},{"version_id":"831618806","version_name":"1.24.0","version_date":"","version_description":""},{"version_id":"832415433","version_name":"1.25.0","version_date":"","version_description":""},{"version_id":"832556775","version_name":"1.25.1","version_date":"","version_description":""},{"version_id":"832680678","version_name":"1.25.2","version_date":"","version_description":""},{"version_id":"832728702","version_name":"1.25.3","version_date":"","version_description":""},{"version_id":"832797558","version_name":"1.26.0","version_date":"","version_description":""},{"version_id":"832923751","version_name":"1.26.1","version_date":"","version_description":""},{"version_id":"833083525","version_name":"1.26.2","version_date":"","version_description":""},{"version_id":"833350288","version_name":"1.27.0","version_date":"","version_description":""},{"version_id":"833350288","version_name":"1.26.3","version_date":"","version_description":""},{"version_id":"833842353","version_name":"1.27.0","version_date":"","version_description":""},{"version_id":"833984786","version_name":"1.27.1","version_date":"","version_description":""},{"version_id":"834239281","version_name":"1.27.2","version_date":"","version_description":""},{"version_id":"834334643","version_name":"1.27.3","version_date":"","version_description":""},{"version_id":"834512984","version_name":"1.27.4","version_date":"","version_description":""},{"version_id":"834754144","version_name":"1.27.5","version_date":"","version_description":""},{"version_id":"834974441","version_name":"1.27.6","version_date":"","version_description":""},{"version_id":"835151373","version_name":"1.27.7","version_date":"","version_description":""},{"version_id":"835228322","version_name":"1.28.0","version_date":"","version_description":""},{"version_id":"835284065","version_name":"1.28.1","version_date":"","version_description":""},{"version_id":"835448634","version_name":"1.28.2","version_date":"","version_description":""},{"version_id":"835494431","version_name":"1.28.3","version_date":"","version_description":""},{"version_id":"835574588","version_name":"1.28.4","version_date":"","version_description":""},{"version_id":"835602019","version_name":"1.28.5","version_date":"","version_description":""},{"version_id":"836282192","version_name":"2.0.0","version_date":"","version_description":""},{"version_id":"836310667","version_name":"2.0.1","version_date":"","version_description":""},{"version_id":"836326527","version_name":"2.0.2","version_date":"","version_description":""},{"version_id":"836344150","version_name":"2.0.3","version_date":"","version_description":""},{"version_id":"836378960","version_name":"2.0.4","version_date":"","version_description":""},{"version_id":"836586191","version_name":"2.0.5","version_date":"","version_description":""},{"version_id":"836601392","version_name":"2.0.6","version_date":"","version_description":""},{"version_id":"836651409","version_name":"2.0.7","version_date":"","version_description":""},{"version_id":"836800157","version_name":"2.0.8","version_date":"","version_description":""},{"version_id":"836926962","version_name":"2.0.9","version_date":"","version_description":""},{"version_id":"837049192","version_name":"2.0.10","version_date":"","version_description":""},{"version_id":"837371605","version_name":"2.0.11","version_date":"","version_description":""},{"version_id":"837452586","version_name":"2.0.12","version_date":"","version_description":""},{"version_id":"837512045","version_name":"2.0.13","version_date":"","version_description":""},{"version_id":"837788011","version_name":"2.0.14","version_date":"","version_description":""},{"version_id":"837892100","version_name":"2.0.15","version_date":"","version_description":""},{"version_id":"837967086","version_name":"2.0.16","version_date":"","version_description":""},{"version_id":"838018252","version_name":"2.0.17","version_date":"","version_description":""},{"version_id":"838066209","version_name":"2.1.0","version_date":"","version_description":""},{"version_id":"838284591","version_name":"2.2.0","version_date":"","version_description":""},{"version_id":"838558950","version_name":"2.2.1","version_date":"","version_description":""},{"version_id":"838809700","version_name":"2.2.2","version_date":"","version_description":""},{"version_id":"839126515","version_name":"2.2.3","version_date":"","version_description":""},{"version_id":"839305900","version_name":"2.2.4","version_date":"","version_description":""},{"version_id":"839334948","version_name":"2.2.5","version_date":"","version_description":""},{"version_id":"839674303","version_name":"2.2.6","version_date":"","version_description":""},{"version_id":"840095578","version_name":"2.3.0","version_date":"","version_description":""},{"version_id":"840149188","version_name":"2.3.1","version_date":"","version_description":""},{"version_id":"840471812","version_name":"2.3.2","version_date":"","version_description":""},{"version_id":"840690889","version_name":"2.3.3","version_date":"","version_description":""},{"version_id":"840902295","version_name":"2.3.4","version_date":"","version_description":""},{"version_id":"841069158","version_name":"2.3.5","version_date":"","version_description":""},{"version_id":"84242644","version_name":"1.2.3","version_date":"","version_description":""},{"version_id":"87262661","version_name":"1.2.4","version_date":"","version_description":""}]