[{"version_id":"822564862","version_name":"1.0.3","version_date":"2017-06-17 04:46:18.000 +0800","version_description":"（1）优化学习室不能正常开始问题\n（2）发现频道体现所有试卷主题，并可挑战最好成绩\n（3）支持好友之间连续PK\n（4）好友消息通知方式优化\n（5）基本GPS定位智能化推荐学校\n  (8)   增加错题本、报错功能"},{"version_id":"822601539","version_name":"1.0.4","version_date":"2017-06-21 06:28:45.000 +0800","version_description":"修复bug。\n\n近期更新内容：\n（1）优化学习室不能正常开始问题\n（2）发现频道体现所有试卷主题，并可挑战最好成绩\n（3）支持好友之间连续PK\n（4）好友消息通知方式优化\n（5）基本GPS定位智能化推荐学校\n  (6)   增加错题本、报错功能"},{"version_id":"823608211","version_name":"1.1.5","version_date":"2017-09-10 01:27:48.000 +0800","version_description":"1.1.5版本更新内容:\n\n1.感兴趣的人优先推荐一起刷过题的好友\n2.同学模块增加活动入口\n3.解决部分版本无学习小组入口问题"},{"version_id":"824092896","version_name":"1.2.1","version_date":"2017-10-22 02:01:35.000 +0800","version_description":"【新玩法】找同学开启“智勇大挑战”刷题集卡换大礼啦！\n  -超过100万+题库等你刷，可与对手边玩边交流\n  -数百上千个超有趣的益智问题等你来回答\n  -不一样的刷题学习模式，可享受对决的刺激，挑战对手赢取卡牌\n  -当你玩的正high不小心要交出答题权时，别急，还可用积分换取机会哦\n  -学而思精选题库、作文赏析应有尽有"},{"version_id":"825248653","version_name":"1.2.2","version_date":"2017-12-09 02:41:06.000 +0800","version_description":"bug修复"},{"version_id":"826162758","version_name":"2.0.2","version_date":"2018-03-03 08:16:14.000 +0800","version_description":"1.学习流程优化，减少操作步骤，让学习更简单\n2.学习内容升级，多讲内容任意学\n3.增加学习奖励机制，激励用户主动学习"},{"version_id":"826254087","version_name":"2.0.3","version_date":"2018-03-15 09:54:58.000 +0800","version_description":"1.增加班级，开通的用户可以和同学一起学习啦\n2.学习顺序由上到下开始学，更符合你的使用习惯\n3.为更好的服务用户，可以在首页【交流】加入组织"},{"version_id":"826818165","version_name":"2.0.6","version_date":"2018-04-28 10:11:22.000 +0800","version_description":"bug修复，让您的应用更流畅。\n\n之前版本的新增内容:\n1.结合学而思7大能力优化课程体系，承接“全日制义务教育数学课程标准 ” 2.优化学习流程，增加学习目标，让学习更有效 3.增加学习进度、班级排名、学习报告等功能 4.打造轻松学习氛围，培养习惯，激发兴趣，塑造品格"},{"version_id":"827670522","version_name":"2.1.3","version_date":"2018-06-28 10:39:01.000 +0800","version_description":"bug修复，性能优化，使用更流畅。\n\n最近更新：\n1.数学主页更新，全景地图引导学习，所有课程一目了然\n2.关注服务号、邀好友课程免费学\n3.新增思维拓展，挑战自己，能力无极限\n4.新增语文学科，寓言故事边玩边学无负担"},{"version_id":"828028551","version_name":"2.3.1","version_date":"2018-07-30 13:58:32.000 +0800","version_description":"1、新增语文专题课程，课程方向：品格培养、成语学习、句式的应用等。\n2、新增数学各种题型的专项习题训练。\n3、新增语音作业功能，帮助孩子培养表达能力。"},{"version_id":"828354928","version_name":"2.5.2","version_date":"2018-09-14 15:00:30.000 +0800","version_description":"性能优化，bug修复。\n\n近期更新内容：\n人教版PEP小学英语外教口语同步课正式上线~\n小学数学动画同步课程正式上线~\n小学语文互动新绘本专题课全新升级~"},{"version_id":"828650571","version_name":"2.7.0","version_date":"2018-10-02 18:47:08.000 +0800","version_description":"1.适配iOS12~\n2.轻课所有课程可通过邀请好友免费学习啦~\n3.人教版数学同步课程新增单元测试、期中、期末测试，课程掌握情况一目了然~\n4.人教版英语课程新增练习环节，针对知识点举一反三巩固练习~\n5.我的家园上线，让学习更有趣~\n6.新增学习计划，培养良好学习习惯~"},{"version_id":"829144920","version_name":"2.7.3","version_date":"2018-11-03 23:20:57.000 +0800","version_description":"1.学习流程简化，让学习更轻松、更简单\n2.答题时再也不怕手抖点错，支持选项修改啦\n3.用户等级体系优化，小红花代替原有验值，后续有惊喜噢"},{"version_id":"829193969","version_name":"3.0.0","version_date":"2018-11-09 10:32:20.000 +0800","version_description":"1.首页全新升级，新增限免课程，更多优质学习内容推荐。\n2.拍教材搜课程功能震撼来袭，拍摄教材书页，秒出视频讲解，其实学习很简单。\n3.新增免费专区，海量精彩课外读物，让学习变得更有趣。\n4.我的页面改版，已学课程、个人信息一目了然，小伙伴们快来看看吧。"},{"version_id":"829248169","version_name":"3.0.1","version_date":"2018-11-12 11:58:35.000 +0800","version_description":"修复bug,性能优化。\n最近更新内容：\n1.首页全新升级，新增限免课程，更多优质学习内容推荐。\n2.拍教材搜课程功能震撼来袭，拍摄教材书页，秒出视频讲解，其实学习很简单。\n3.新增免费专区，海量精彩课外读物，让学习变得更有趣。\n4.我的页面改版，已学课程、个人信息一目了然，小伙伴们快来看看吧。"},{"version_id":"829263596","version_name":"3.0.2","version_date":"2018-11-22 10:12:21.000 +0800","version_description":"1.拍照搜课程功能优化。\n2.发现模块视频播放功能优化。"},{"version_id":"829382212","version_name":"3.0.3","version_date":"2018-12-11 13:32:28.000 +0800","version_description":"bug修复 ，性能优化。"},{"version_id":"829615538","version_name":"3.0.5","version_date":"2018-12-14 11:47:25.000 +0800","version_description":"修复bug，优化性能。"},{"version_id":"829766686","version_name":"3.2.0","version_date":"2018-12-31 10:43:29.000 +0800","version_description":"1.新增部教版同步课程，支持语音跟读、配音，预习复习一招搞定。\n2.学科地图页全新大改版，新增单元宝箱与学习进度，学习情况一目了然。\n3.邀请同学完成学习计划，获取稀有建筑、精灵；完成周计划还有阶段奖励哦。\n4.消息中心正式上线，让您和孩子不错过每个重要学习通知。\n5.班级动态支持好友点赞，大图查看，和大家一起快乐学习。\n6.班级排名新增成就榜和小红花周榜，和小伙伴比一比。\n7.家园支持切换不同场景，新增动画，还有隐藏小彩蛋哦~\n8.家园新增繁荣度，学习奖励越多，家园越繁荣，快快努力学习吧~\n9.可以给小伙伴的家园点赞啦，还能拍照分享自己的家园哦~"},{"version_id":"829971608","version_name":"3.3.0","version_date":"2019-01-28 15:21:30.000 +0800","version_description":"1、数学、英语体验营全面上线，制定专属学习计划，领取学习权限~\n2、数学挑战小魔王环节优化规则啦，快和小魔王PK下吧~\n3、部编版语文也能拍照搜课啦，拿出课本，即拍即看~\n4、新增部编版语文下册课程、人教版英语下册课程~\n5、英语课程也能用学习卡学习啦，快跟上老师的步伐吧~"},{"version_id":"830592669","version_name":"3.5.0","version_date":"2019-03-21 11:09:31.000 +0800","version_description":"1、【轻课改版】页面全新改版，多科课程随意学~\n2、【通识课】新增精品通识课，成就孩子未来更多可能~\n3、【训练班】专项提升训练班上线，免费报名领取上课权限和优惠福利~\n4、【小红花】小红花商城上线啦，完成学习就能兑换你喜欢的家园道具啦~\n5、【英语】PEP英语同步课全新学习体验，外教互动短视频课程，让英语学习更轻松~\n6、【班级】班级全新改版，新增班级周报，班级列表和年级动态~\n7、【已学课程】已学课程入口统一，进度明了，服务更贴心~\n8、【消息】消息中心移至“我的”页面，重要学习消息不错过~"},{"version_id":"830861316","version_name":"3.6.0","version_date":"2019-04-06 16:45:32.000 +0800","version_description":"1、【训练班】训练班添加打卡和分享，叫上同学一起学习吧~\n2、【班级】部编版语文也可以加入班级啦~\n3、【任务】每日任务全新改版，增加活跃度奖励~"},{"version_id":"830941392","version_name":"3.7.0","version_date":"2019-04-12 23:06:07.000 +0800","version_description":"优化了数学学科的学习体验\n- 错题集上线，自己错题随时学，查漏补缺不发愁\n- 学习过程中使用体验改善，提高孩子学习效率"},{"version_id":"831001264","version_name":"3.8.0","version_date":"2019-04-18 10:27:12.000 +0800","version_description":"性能优化"},{"version_id":"831099583","version_name":"3.9.0","version_date":"2019-05-02 22:58:41.000 +0800","version_description":"【新功能】语数外专项突破班开班啦！选材对标各学科重要能力，突破瓶颈，提升学力～\n【新课程】英语单词专题课上线啦！制作团队研发3月，精品趣味互动课程，助力孩子打牢词汇基本功～\n【新优化】专项训练班正式开启，全新学习体验～"},{"version_id":"831384394","version_name":"4.0.0","version_date":"2019-05-23 11:43:13.000 +0800","version_description":"1、【训练班】学习计划页改版，专属海报动态生成，完成学习送学而思秘籍，包邮哦~\n2、【专题课】英语专题课学习体验升级，交互更便捷，更好地助力孩子打牢词汇基本功~\n3、【新优化】专题课学习流程优化，全新学习体验正式开启~"},{"version_id":"831517176","version_name":"4.1.1","version_date":"2019-06-03 09:58:41.000 +0800","version_description":"- 优化iPad大屏视觉体验\n- 调整首页课程显示布局，让您更快更好找到课程\n- 调整班级页面布局\n- 我的课程，班级页面显示优化\n- 本讲目标，成绩单优化\n- 优化显示效果\n- 修复已知问题"},{"version_id":"831682987","version_name":"4.2.0","version_date":"2019-06-20 11:19:37.000 +0800","version_description":"修复bug，优化用户体验。"},{"version_id":"831738061","version_name":"4.3.0","version_date":"2019-06-24 10:44:50.000 +0800","version_description":"1、用户可匿名浏览～\n2、用户体验优化～"},{"version_id":"831831447","version_name":"4.4.0","version_date":"2019-07-03 19:59:41.000 +0800","version_description":"【改版升级】“任务中心”全面改版，参与任务获取学币，更多课程免费学\n【优化升级】课程年级筛选更便捷，用户体验更舒适\n【功能优化】“班级”转移至首页，一键进班级，快速了解班级新动态"},{"version_id":"832041765","version_name":"4.5.0","version_date":"2019-07-19 12:41:29.000 +0800","version_description":"【首页改版】首页界面优化，学习更便捷~\n【新增频道】新增素养课频道，精选课程一目了然~\n【标签优化】支持教材筛选，操作更方便~"},{"version_id":"832192996","version_name":"4.6.0","version_date":"2019-08-05 10:58:19.000 +0800","version_description":"【新增课程】新增英语专题互动课，听说读写全面提升~\n【新增课程】“勇士秘境”全新上线，助力数学思维提升~\n【全新体验】动画+阅读创造性结合，让学习更加高效~"},{"version_id":"832282155","version_name":"4.7.0","version_date":"2019-08-08 11:31:21.000 +0800","version_description":"【课程升级】数学同步课新升级，直播互动学习更有效~\n【新增课程】初中课程趣味上线，课内重点边学边玩~"},{"version_id":"832346440","version_name":"4.7.1","version_date":"2019-08-15 16:30:05.000 +0800","version_description":"修复bug\n\n近期更新:\n【课程升级】数学同步课新升级，直播互动学习更有效~\n【新增课程】初中课程趣味上线，课内重点边学边玩~"},{"version_id":"832432158","version_name":"4.8.0","version_date":"2019-08-25 15:41:01.000 +0800","version_description":"【体验优化】用户体验优化，互动学习更流畅~"},{"version_id":"832512546","version_name":"4.9.0","version_date":"2019-08-31 11:57:43.000 +0800","version_description":"【内容升级】小学1-6年级语数外同步课全覆盖~\n【体验升级】全新AI互动+直播课，趣味学习更有效~\n【产品优化】用户体验优化，互动学习更流畅~"},{"version_id":"832662697","version_name":"4.9.1","version_date":"2019-09-09 11:06:32.000 +0800","version_description":"【体验升级】快速进入直播课堂，互动学习效果好~\n【功能优化】精准识别录音音频，跟读朗诵趣味多~\n【视觉升级】优化视频播放流畅度，在线观看课程不卡顿~"},{"version_id":"832837668","version_name":"5.0.0","version_date":"2019-09-23 20:45:14.000 +0800","version_description":"【课程升级】归纳课内知识点，提升课外知识面~\n【体验升级】登录体验新升级，学习课程更便捷~\n【福利专区】快乐学习领金币，还能兑换课程优惠券~"},{"version_id":"832952497","version_name":"5.0.1","version_date":"2019-09-30 15:37:53.000 +0800","version_description":"【适配优化】紧随科技脚步，进行iOS13应用兼容性适配~\n【体验升级】提升用户体验，观看视频课程更流畅~"},{"version_id":"833079712","version_name":"5.1.0","version_date":"2019-10-11 11:31:14.000 +0800","version_description":"【视觉升级】家园场景全新升级，横屏展示视觉超震撼~\n【功能优化】新增等级系统，等级越高领地越多~\n【趣味激励】快乐学习开宝箱，获取稀有材料“魔法水晶”~\n【福利专区】积极参与AI互动课，福利红包等你来抢~"},{"version_id":"833133309","version_name":"5.2.0","version_date":"2019-10-14 14:18:34.000 +0800","version_description":"【功能优化】双师在线教学，全面互动，有效学习~\n【界面优化】视觉效果新升级，打卡学习体验更流畅~\n【产品优化】优化用户体验性能，小学生使用更方便~"},{"version_id":"833198535","version_name":"5.3.0","version_date":"2019-10-17 14:37:57.000 +0800","version_description":"【体验优化】优化用户交互体验，快乐打卡轻松学～\n【活动福利】趣味学习活动新上线，快来参加～"},{"version_id":"833340247","version_name":"5.4.0","version_date":"2019-10-29 16:21:33.000 +0800","version_description":"【产品优化】学习计划新升级，高效学习还能培养学习好习惯~\n【体验升级】账号登录更方便，用户体验超便捷~"},{"version_id":"833396863","version_name":"5.4.1","version_date":"2019-10-31 12:04:24.000 +0800","version_description":"【产品优化】学习计划新升级，高效学习还能培养学习好习惯~\n【体验升级】账号登录更方便，用户体验超便捷~"},{"version_id":"833435369","version_name":"5.5.0","version_date":"2019-11-06 15:35:30.000 +0800","version_description":"【课程升级】新增Raz独家课程，哈佛牛津外教亲授~\n【体验升级】AI智能互动，全面提升孩子英语能力~\n【产品升级】Raz分级读物，听、说、读全方位培养孩子英语能力~"},{"version_id":"833571178","version_name":"5.6.0","version_date":"2019-11-13 17:30:10.000 +0800","version_description":"【功能升级】家园开放至10级，开启装扮功能~\r\n【产品优化】任务页面新升级，新增拍照搜课功能~\r\n【体验升级】提升用户使用舒适度，优化家园界面~"},{"version_id":"833624401","version_name":"5.7.0","version_date":"2019-11-21 14:50:44.000 +0800","version_description":"【产品优化】学习计划新升级，制定计划更方便~\n【体验升级】互动学习多样化，独立学习趣味多~"},{"version_id":"833746368","version_name":"5.7.1","version_date":"2019-11-26 18:27:55.000 +0800","version_description":"【产品优化】学习计划新升级，制定计划更方便~\n【体验升级】互动学习多样化，独立学习趣味多~"},{"version_id":"833809588","version_name":"5.9.0","version_date":"2019-12-10 14:16:08.000 +0800","version_description":"【功能优化】新增练习场功能，海量boss等你来挑战~\n【产品优化】数学学习报告优化升级，学习成果随时可见~\n【体验升级】参与课程评价，快来一起分享你的学习感受吧~"},{"version_id":"834054638","version_name":"6.0.0","version_date":"2019-12-26 00:31:12.000 +0800","version_description":"【产品优化】一键登录学习超方便，快乐学习效率高~\n【体验升级】提升界面细节美化，保护视力不疲劳~"},{"version_id":"834139472","version_name":"6.1.0","version_date":"2020-01-07 11:17:23.000 +0800","version_description":"【产品优化】一键登录学习超方便，快乐学习效率高~\n【体验升级】提升界面细节美化，保护视力不疲劳~"},{"version_id":"834269127","version_name":"6.2.0","version_date":"2020-01-13 10:43:30.000 +0800","version_description":"【课程升级】语数外下册课程新增AI定时直播课！\n【品牌升级】学而思轻课图标大更换，熊猫形象超可爱！\n【视觉升级】页面增加情感化设计，视觉体验更温暖"},{"version_id":"834357811","version_name":"6.3.0","version_date":"2020-01-16 12:15:06.000 +0800","version_description":"【功能升级】新增会员拼团功能，拼着买更划算~\n【页面优化】学习页面新优化，快乐学习更轻松！"},{"version_id":"834703120","version_name":"6.4.0","version_date":"2020-02-14 10:17:34.000 +0800","version_description":"【课程升级】新年上新课，小学生们都爱看~\n【体验升级】用户学习体验升级，互动交流更有趣~\n【产品优化】视觉设计精美化，天真童趣真好看~"},{"version_id":"834728628","version_name":"6.5.0","version_date":"2020-02-16 14:03:48.000 +0800","version_description":"【体验升级】AI直播课大升级，互动学习效率高～\n【课程推荐】足不出户，小学语数外同步课在线学～"},{"version_id":"834840256","version_name":"6.6.0","version_date":"2020-02-25 11:06:28.000 +0800","version_description":"【体验升级】优化语音评测，互动体验更流畅"},{"version_id":"834955613","version_name":"6.6.2","version_date":"2020-03-04 09:45:56.000 +0800","version_description":"【体验升级】优化语音评测，学习体验更流畅~"},{"version_id":"834986265","version_name":"6.6.3","version_date":"2020-03-06 10:30:17.000 +0800","version_description":"【产品优化】系统优化大升级，安全学习家长更放心~"},{"version_id":"835040876","version_name":"7.0.0","version_date":"2020-03-11 12:17:50.000 +0800","version_description":"【体验升级】课程学习体验全面升级，学习过程更流畅、更简单！\n【界面优化】视觉效果升级，学习界面更美观！\n【系统升级】改善学习体验效果，提升互动稳定性！"},{"version_id":"835135331","version_name":"7.0.1","version_date":"2020-03-20 13:56:44.000 +0800","version_description":"【产品升级】AI直播课优化升级，互动学习有趣又流畅！\n【系统升级】改善学习体验效果，提升互动稳定性！"},{"version_id":"835224463","version_name":"7.0.2","version_date":"2020-03-30 09:56:06.000 +0800","version_description":"【产品升级】小任务，大奖励，每天动手领福利！\n【体验升级】课程学习体验全面升级，学习过程更流畅！"},{"version_id":"835324160","version_name":"7.0.3","version_date":"2020-04-02 12:40:15.000 +0800","version_description":"【功能升级】快速添加班主任微信，师生互动学习效率高！\n【体验升级】学习体验轻优化，课内课外知识记得牢！"},{"version_id":"835540189","version_name":"7.1.0","version_date":"2020-04-21 10:29:13.000 +0800","version_description":"【功能升级】支持语文课文跟读、古诗配音全面升级！\n【系统升级】改善学习体验效果，提升互动稳定性！"},{"version_id":"835642592","version_name":"7.1.1","version_date":"2020-04-30 12:12:33.000 +0800","version_description":"【界面优化】视觉效果升级，学习界面更美观！\n【系统升级】改善学习体验效果，提升互动稳定性！"},{"version_id":"835837157","version_name":"7.1.2","version_date":"2020-05-22 14:07:34.000 +0800","version_description":"【体验升级】学习体验轻优化，课内课外知识记得牢！\n 【界面优化】视觉效果升级，学习界面更美观！"},{"version_id":"836098850","version_name":"7.1.2","version_date":"2020-05-22 14:07:34.000 +0800","version_description":"【体验升级】学习体验轻优化，课内课外知识记得牢！\n 【界面优化】视觉效果升级，学习界面更美观！"},{"version_id":"836254187","version_name":"7.2.0","version_date":"2020-06-15 14:22:13.000 +0800","version_description":"首页全新改版，邀请您来体验！\r\n-首页模块全新改版，课程、教材、体验课清晰呈现，便捷学习入口，掌握知识更高效！\r\n-新增自适应推荐区，智能推荐最适合我的课程，免费试听，随时随地开始学习！\r\n-暑秋课程全面上线，趣味Ai互动课堂，轻松完成预习复习，领跑新学期！\r"},{"version_id":"836756326","version_name":"7.3.0","version_date":"2020-07-13 22:34:27.000 +0800","version_description":"本次更新：\n-首页上线专项提升训练班快速报名入口，不再错过好课程！\n-新增综合训练班，支持多学科同步学习！"},{"version_id":"836962715","version_name":"7.3.1","version_date":"2020-07-24 10:31:03.000 +0800","version_description":"本次更新：\r\n-首页上线专项提升训练班快速报名入口，不再错过好课程！\r\n-新增综合训练班，支持多学科同步学习！\r\n-修复了一些bug。"},{"version_id":"837023437","version_name":"7.3.2","version_date":"2020-07-28 10:54:09.000 +0800","version_description":"本次更新：\r\n-首页上线专项提升训练班快速报名入口，不再错过好课程！\r\n-新增综合训练班，支持多学科同步学习！\r\n-修复了一些bug。"},{"version_id":"837331836","version_name":"7.4.1","version_date":"2020-08-13 14:58:41.000 +0800","version_description":"本次更新：\n-首页全新上线语数英综合训练班，【我的】页面随时查看训练班进度！\n-首页新增搜索入口，海量优质学习内容高效搜索！\n-全新学科地图页，更清晰的学习路径，帮助孩子高效学习！\n-优化部分功能，提升做题体验~"},{"version_id":"837464012","version_name":"7.5.0","version_date":"2020-08-24 16:37:34.000 +0800","version_description":"本次更新：\r\n-数学秋季课程新增真人互动课，新增【预习同步练习】，帮助孩子夯实基础知识！\r\n-英语秋季课程新增【漫画点读预习】，探索式学习激发孩子兴趣；新增【趣味拼读拖拽发音】，让孩子轻松掌握拼读技巧！"},{"version_id":"837942341","version_name":"7.6.0","version_date":"2020-09-25 21:56:23.000 +0800","version_description":"本次更新：\r\n-新增「错题本」功能，随时改错巩固各科知识，高效学习！"},{"version_id":"838226766","version_name":"7.7.0","version_date":"2020-10-19 15:06:45.000 +0800","version_description":"本次更新：\r\n-语数英学科地图页优化部分功能，提升学习体验！"},{"version_id":"838513368","version_name":"7.7.1","version_date":"2020-11-24 15:57:30.000 +0800","version_description":"本次更新：\r\n-优化课程学习记录，提升学习体验！"},{"version_id":"839394329","version_name":"7.7.2","version_date":"2020-12-02 19:34:01.000 +0800","version_description":"本次更新：\r\n-修复一些bug，提升学习体验！"},{"version_id":"839550722","version_name":"7.7.3","version_date":"2020-12-11 14:47:27.000 +0800","version_description":"本次更新：\r\n-修复一些bug，提升学习体验！"},{"version_id":"840348422","version_name":"7.8.1","version_date":"2021-02-18 21:07:10.000 +0800","version_description":"本次更新：\r\n-上新新春活动！\r\n-优化部分功能，提升学习体验！"},{"version_id":"840861639","version_name":"7.8.3","version_date":"2021-03-17 12:52:38.000 +0800","version_description":"本次更新：\r\n-优化部分功能，提升学习体验！"},{"version_id":"841042910","version_name":"7.8.4","version_date":"2021-03-26 15:45:20.000 +0800","version_description":"本次更新：\r\n-优化部分功能，提升学习体验！"}]